<?xml version="1.0" encoding="UTF-8"?>
<SunopsisExport>
<Admin RepositoryVersion="05.02.02.05" IsLegacyIdCompatible="false" />
<Encryption algorithm="AES" keyLength="128" exportKeyHash="FwObG8jeCPf1jRP0ucee6dA9corfS/vV2bEjfTeM43o=" keyVect="zxNr9iR1fFzq9QQQkPuPHA==" exportKeySalt="15c0c8d9-824b-4b7d-8d5c-a21e8ab0e794" containsCipherText="false"/>
<Object class="com.sunopsis.dwg.dbobj.SnpTable">
		<Field name="ExtVersion" type="java.lang.String">null</Field>
	<Field name="FileDecSep" type="java.lang.String">null</Field>
	<Field name="FileEncField" type="java.lang.String">null</Field>
	<Field name="FileEscChar" type="java.lang.String">null</Field>
	<Field name="FileFirstRow" type="com.sunopsis.sql.DbInt"><![CDATA[null]]></Field>
	<Field name="FileFormat" type="java.lang.String">null</Field>
	<Field name="FileNullValue" type="java.lang.String">null</Field>
	<Field name="FileSepColl" type="java.lang.String">null</Field>
	<Field name="FileSepField" type="java.lang.String">null</Field>
	<Field name="FileSepMap" type="java.lang.String">null</Field>
	<Field name="FileSepRow" type="java.lang.String">null</Field>
	<Field name="FirstDate" type="java.sql.Timestamp"><![CDATA[2017-02-17 15:27:01.0]]></Field>
	<Field name="FirstUser" type="java.lang.String"><![CDATA[SUPERVISOR]]></Field>
	<Field name="GlobalId" type="java.lang.String"><![CDATA[35a37bac-712d-4394-8a0e-a8c20de2b96d]]></Field>
	<Field name="HiveBuckets" type="com.sunopsis.sql.DbInt"><![CDATA[null]]></Field>
	<Field name="HiveLocation" type="java.lang.String">null</Field>
	<Field name="HiveRowFormat" type="java.lang.String">null</Field>
	<Field name="IndChange" type="java.lang.String"><![CDATA[U]]></Field>
	<Field name="IndErrDel" type="java.lang.String">null</Field>
	<Field name="IndFilePosAuto" type="java.lang.String">null</Field>
	<Field name="IndHiveManaged" type="java.lang.String">null</Field>
	<Field name="IndHiveNative" type="java.lang.String">null</Field>
	<Field name="IndJrn" type="java.lang.String"><![CDATA[0]]></Field>
	<Field name="IndShow" type="java.lang.String"><![CDATA[1]]></Field>
	<Field name="IndWs" type="java.lang.String">null</Field>
	<Field name="InputFormat" type="java.lang.String">null</Field>
	<Field name="IntVersion" type="com.sunopsis.sql.DbInt"><![CDATA[1]]></Field>
	<Field name="IMod" type="com.sunopsis.sql.DbInt"><![CDATA[95]]></Field>
	<Field name="IScBaseTable" type="com.sunopsis.sql.DbInt"><![CDATA[null]]></Field>
	<Field name="IScOrigTable" type="com.sunopsis.sql.DbInt"><![CDATA[null]]></Field>
	<Field name="IScTable" type="com.sunopsis.sql.DbInt"><![CDATA[null]]></Field>
	<Field name="ISubModel" type="com.sunopsis.sql.DbInt"><![CDATA[166]]></Field>
	<Field name="ITable" type="com.sunopsis.sql.DbInt"><![CDATA[597]]></Field>
	<Field name="ITableFormatType" type="com.sunopsis.sql.DbInt"><![CDATA[null]]></Field>
	<Field name="ITxtDesc" type="com.sunopsis.sql.DbInt"><![CDATA[null]]></Field>
	<Field name="ITxtWsdl" type="com.sunopsis.sql.DbInt"><![CDATA[null]]></Field>
	<Field name="JrnOrder" type="com.sunopsis.sql.DbInt"><![CDATA[null]]></Field>
	<Field name="LastDate" type="java.sql.Timestamp"><![CDATA[2017-02-17 15:27:02.0]]></Field>
	<Field name="LastUser" type="java.lang.String"><![CDATA[SUPERVISOR]]></Field>
	<Field name="OlapType" type="java.lang.String">null</Field>
	<Field name="OutputFormat" type="java.lang.String">null</Field>
	<Field name="PartitionMeth" type="java.lang.String">null</Field>
	<Field name="ResName" type="java.lang.String"><![CDATA[OPR_INCIDENT_DTLS]]></Field>
	<Field name="RCount" type="com.sunopsis.sql.DbInt"><![CDATA[null]]></Field>
	<Field name="SchemaFile" type="java.lang.String">null</Field>
	<Field name="ScOrigTableTag" type="java.lang.String">null</Field>
	<Field name="Serde" type="java.lang.String">null</Field>
	<Field name="SerdeProp" type="java.lang.String">null</Field>
	<Field name="StorageHandler" type="java.lang.String">null</Field>
	<Field name="StorageProp" type="java.lang.String">null</Field>
	<Field name="SubPartitionMeth" type="java.lang.String">null</Field>
	<Field name="TableAlias" type="java.lang.String"><![CDATA[OPR_INCIDENT_DTLS]]></Field>
	<Field name="TableName" type="java.lang.String"><![CDATA[OPR_INCIDENT_DTLS]]></Field>
	<Field name="TableProp" type="java.lang.String">null</Field>
	<Field name="TableType" type="java.lang.String"><![CDATA[T]]></Field>
	<Field name="WsEntityName" type="java.lang.String">null</Field>
	<Field name="WsName" type="java.lang.String">null</Field>
</Object>
<Object class="com.sunopsis.dwg.dbobj.SnpCol">
		<Field name="Bytes" type="com.sunopsis.sql.DbInt"><![CDATA[0]]></Field>
	<Field name="CheckFlow" type="java.lang.String"><![CDATA[1]]></Field>
	<Field name="CheckStat" type="java.lang.String"><![CDATA[0]]></Field>
	<Field name="ColDecSep" type="java.lang.String">null</Field>
	<Field name="ColFormat" type="java.lang.String">null</Field>
	<Field name="ColHeading" type="java.lang.String"><![CDATA[INCIDENT_NUMBER]]></Field>
	<Field name="ColMandatory" type="java.lang.String"><![CDATA[1]]></Field>
	<Field name="ColName" type="java.lang.String"><![CDATA[INCIDENT_NUMBER]]></Field>
	<Field name="ColNullIfErr" type="java.lang.String">null</Field>
	<Field name="DataFormat" type="java.lang.String">null</Field>
	<Field name="DefValue" type="java.lang.String">null</Field>
	<Field name="ExtVersion" type="java.lang.String">null</Field>
	<Field name="FilePos" type="com.sunopsis.sql.DbInt"><![CDATA[null]]></Field>
	<Field name="FirstDate" type="java.sql.Timestamp"><![CDATA[2017-02-17 15:27:01.0]]></Field>
	<Field name="FirstUser" type="java.lang.String"><![CDATA[SUPERVISOR]]></Field>
	<Field name="GlobalId" type="java.lang.String"><![CDATA[3c3a52c6-8abb-4c9b-86ce-400007a671a3]]></Field>
	<Field name="HbaseEncoding" type="java.lang.String">null</Field>
	<Field name="HiveSortbyPos" type="com.sunopsis.sql.DbInt"><![CDATA[null]]></Field>
	<Field name="IndChange" type="java.lang.String"><![CDATA[I]]></Field>
	<Field name="IndHiveCluster" type="java.lang.String">null</Field>
	<Field name="IndHivePartition" type="java.lang.String">null</Field>
	<Field name="IndHiveSort" type="java.lang.String">null</Field>
	<Field name="IndIn" type="java.lang.String">null</Field>
	<Field name="IndOut" type="java.lang.String">null</Field>
	<Field name="IndWrite" type="java.lang.String"><![CDATA[1]]></Field>
	<Field name="IndWsInsert" type="java.lang.String"><![CDATA[1]]></Field>
	<Field name="IndWsSelect" type="java.lang.String"><![CDATA[1]]></Field>
	<Field name="IndWsUpdate" type="java.lang.String"><![CDATA[1]]></Field>
	<Field name="IntVersion" type="com.sunopsis.sql.DbInt"><![CDATA[1]]></Field>
	<Field name="ICol" type="com.sunopsis.sql.DbInt"><![CDATA[28484]]></Field>
	<Field name="ISrcCol" type="com.sunopsis.sql.DbInt"><![CDATA[null]]></Field>
	<Field name="ITable" type="com.sunopsis.sql.DbInt"><![CDATA[597]]></Field>
	<Field name="ITxtColDesc" type="com.sunopsis.sql.DbInt"><![CDATA[null]]></Field>
	<Field name="LastDate" type="java.sql.Timestamp"><![CDATA[2017-02-17 15:27:01.0]]></Field>
	<Field name="LastUser" type="java.lang.String"><![CDATA[SUPERVISOR]]></Field>
	<Field name="Longc" type="com.sunopsis.sql.DbInt"><![CDATA[50]]></Field>
	<Field name="Pos" type="com.sunopsis.sql.DbInt"><![CDATA[1]]></Field>
	<Field name="RecCodeList" type="java.lang.String">null</Field>
	<Field name="Scalec" type="com.sunopsis.sql.DbInt"><![CDATA[null]]></Field>
	<Field name="ScdColType" type="java.lang.String">null</Field>
	<Field name="SourceDt" type="java.lang.String"><![CDATA[VARCHAR2]]></Field>
</Object>
<Object class="com.sunopsis.dwg.dbobj.SnpCol">
		<Field name="Bytes" type="com.sunopsis.sql.DbInt"><![CDATA[0]]></Field>
	<Field name="CheckFlow" type="java.lang.String"><![CDATA[1]]></Field>
	<Field name="CheckStat" type="java.lang.String"><![CDATA[0]]></Field>
	<Field name="ColDecSep" type="java.lang.String">null</Field>
	<Field name="ColFormat" type="java.lang.String">null</Field>
	<Field name="ColHeading" type="java.lang.String"><![CDATA[CREATED]]></Field>
	<Field name="ColMandatory" type="java.lang.String"><![CDATA[1]]></Field>
	<Field name="ColName" type="java.lang.String"><![CDATA[CREATED]]></Field>
	<Field name="ColNullIfErr" type="java.lang.String">null</Field>
	<Field name="DataFormat" type="java.lang.String">null</Field>
	<Field name="DefValue" type="java.lang.String">null</Field>
	<Field name="ExtVersion" type="java.lang.String">null</Field>
	<Field name="FilePos" type="com.sunopsis.sql.DbInt"><![CDATA[null]]></Field>
	<Field name="FirstDate" type="java.sql.Timestamp"><![CDATA[2017-02-17 15:27:01.0]]></Field>
	<Field name="FirstUser" type="java.lang.String"><![CDATA[SUPERVISOR]]></Field>
	<Field name="GlobalId" type="java.lang.String"><![CDATA[2214307f-5b26-4282-9fa8-0da57b2f3716]]></Field>
	<Field name="HbaseEncoding" type="java.lang.String">null</Field>
	<Field name="HiveSortbyPos" type="com.sunopsis.sql.DbInt"><![CDATA[null]]></Field>
	<Field name="IndChange" type="java.lang.String"><![CDATA[I]]></Field>
	<Field name="IndHiveCluster" type="java.lang.String">null</Field>
	<Field name="IndHivePartition" type="java.lang.String">null</Field>
	<Field name="IndHiveSort" type="java.lang.String">null</Field>
	<Field name="IndIn" type="java.lang.String">null</Field>
	<Field name="IndOut" type="java.lang.String">null</Field>
	<Field name="IndWrite" type="java.lang.String"><![CDATA[1]]></Field>
	<Field name="IndWsInsert" type="java.lang.String"><![CDATA[1]]></Field>
	<Field name="IndWsSelect" type="java.lang.String"><![CDATA[1]]></Field>
	<Field name="IndWsUpdate" type="java.lang.String"><![CDATA[1]]></Field>
	<Field name="IntVersion" type="com.sunopsis.sql.DbInt"><![CDATA[1]]></Field>
	<Field name="ICol" type="com.sunopsis.sql.DbInt"><![CDATA[28480]]></Field>
	<Field name="ISrcCol" type="com.sunopsis.sql.DbInt"><![CDATA[null]]></Field>
	<Field name="ITable" type="com.sunopsis.sql.DbInt"><![CDATA[597]]></Field>
	<Field name="ITxtColDesc" type="com.sunopsis.sql.DbInt"><![CDATA[null]]></Field>
	<Field name="LastDate" type="java.sql.Timestamp"><![CDATA[2017-02-17 15:27:01.0]]></Field>
	<Field name="LastUser" type="java.lang.String"><![CDATA[SUPERVISOR]]></Field>
	<Field name="Longc" type="com.sunopsis.sql.DbInt"><![CDATA[null]]></Field>
	<Field name="Pos" type="com.sunopsis.sql.DbInt"><![CDATA[2]]></Field>
	<Field name="RecCodeList" type="java.lang.String">null</Field>
	<Field name="Scalec" type="com.sunopsis.sql.DbInt"><![CDATA[null]]></Field>
	<Field name="ScdColType" type="java.lang.String">null</Field>
	<Field name="SourceDt" type="java.lang.String"><![CDATA[DATE]]></Field>
</Object>
<Object class="com.sunopsis.dwg.dbobj.SnpCol">
		<Field name="Bytes" type="com.sunopsis.sql.DbInt"><![CDATA[0]]></Field>
	<Field name="CheckFlow" type="java.lang.String"><![CDATA[1]]></Field>
	<Field name="CheckStat" type="java.lang.String"><![CDATA[0]]></Field>
	<Field name="ColDecSep" type="java.lang.String">null</Field>
	<Field name="ColFormat" type="java.lang.String">null</Field>
	<Field name="ColHeading" type="java.lang.String"><![CDATA[CREATED_DT]]></Field>
	<Field name="ColMandatory" type="java.lang.String"><![CDATA[0]]></Field>
	<Field name="ColName" type="java.lang.String"><![CDATA[CREATED_DT]]></Field>
	<Field name="ColNullIfErr" type="java.lang.String">null</Field>
	<Field name="DataFormat" type="java.lang.String">null</Field>
	<Field name="DefValue" type="java.lang.String">null</Field>
	<Field name="ExtVersion" type="java.lang.String">null</Field>
	<Field name="FilePos" type="com.sunopsis.sql.DbInt"><![CDATA[null]]></Field>
	<Field name="FirstDate" type="java.sql.Timestamp"><![CDATA[2017-02-17 15:27:01.0]]></Field>
	<Field name="FirstUser" type="java.lang.String"><![CDATA[SUPERVISOR]]></Field>
	<Field name="GlobalId" type="java.lang.String"><![CDATA[b1cc0399-46bf-4a03-9e7d-a481ab61ce2b]]></Field>
	<Field name="HbaseEncoding" type="java.lang.String">null</Field>
	<Field name="HiveSortbyPos" type="com.sunopsis.sql.DbInt"><![CDATA[null]]></Field>
	<Field name="IndChange" type="java.lang.String"><![CDATA[I]]></Field>
	<Field name="IndHiveCluster" type="java.lang.String">null</Field>
	<Field name="IndHivePartition" type="java.lang.String">null</Field>
	<Field name="IndHiveSort" type="java.lang.String">null</Field>
	<Field name="IndIn" type="java.lang.String">null</Field>
	<Field name="IndOut" type="java.lang.String">null</Field>
	<Field name="IndWrite" type="java.lang.String"><![CDATA[1]]></Field>
	<Field name="IndWsInsert" type="java.lang.String"><![CDATA[1]]></Field>
	<Field name="IndWsSelect" type="java.lang.String"><![CDATA[1]]></Field>
	<Field name="IndWsUpdate" type="java.lang.String"><![CDATA[1]]></Field>
	<Field name="IntVersion" type="com.sunopsis.sql.DbInt"><![CDATA[1]]></Field>
	<Field name="ICol" type="com.sunopsis.sql.DbInt"><![CDATA[28481]]></Field>
	<Field name="ISrcCol" type="com.sunopsis.sql.DbInt"><![CDATA[null]]></Field>
	<Field name="ITable" type="com.sunopsis.sql.DbInt"><![CDATA[597]]></Field>
	<Field name="ITxtColDesc" type="com.sunopsis.sql.DbInt"><![CDATA[null]]></Field>
	<Field name="LastDate" type="java.sql.Timestamp"><![CDATA[2017-02-17 15:27:01.0]]></Field>
	<Field name="LastUser" type="java.lang.String"><![CDATA[SUPERVISOR]]></Field>
	<Field name="Longc" type="com.sunopsis.sql.DbInt"><![CDATA[null]]></Field>
	<Field name="Pos" type="com.sunopsis.sql.DbInt"><![CDATA[3]]></Field>
	<Field name="RecCodeList" type="java.lang.String">null</Field>
	<Field name="Scalec" type="com.sunopsis.sql.DbInt"><![CDATA[null]]></Field>
	<Field name="ScdColType" type="java.lang.String">null</Field>
	<Field name="SourceDt" type="java.lang.String"><![CDATA[DATE]]></Field>
</Object>
<Object class="com.sunopsis.dwg.dbobj.SnpCol">
		<Field name="Bytes" type="com.sunopsis.sql.DbInt"><![CDATA[0]]></Field>
	<Field name="CheckFlow" type="java.lang.String"><![CDATA[1]]></Field>
	<Field name="CheckStat" type="java.lang.String"><![CDATA[0]]></Field>
	<Field name="ColDecSep" type="java.lang.String">null</Field>
	<Field name="ColFormat" type="java.lang.String">null</Field>
	<Field name="ColHeading" type="java.lang.String"><![CDATA[STATE]]></Field>
	<Field name="ColMandatory" type="java.lang.String"><![CDATA[0]]></Field>
	<Field name="ColName" type="java.lang.String"><![CDATA[STATE]]></Field>
	<Field name="ColNullIfErr" type="java.lang.String">null</Field>
	<Field name="DataFormat" type="java.lang.String">null</Field>
	<Field name="DefValue" type="java.lang.String">null</Field>
	<Field name="ExtVersion" type="java.lang.String">null</Field>
	<Field name="FilePos" type="com.sunopsis.sql.DbInt"><![CDATA[null]]></Field>
	<Field name="FirstDate" type="java.sql.Timestamp"><![CDATA[2017-02-17 15:27:02.0]]></Field>
	<Field name="FirstUser" type="java.lang.String"><![CDATA[SUPERVISOR]]></Field>
	<Field name="GlobalId" type="java.lang.String"><![CDATA[19184d01-904c-4490-803e-f1066bf3a103]]></Field>
	<Field name="HbaseEncoding" type="java.lang.String">null</Field>
	<Field name="HiveSortbyPos" type="com.sunopsis.sql.DbInt"><![CDATA[null]]></Field>
	<Field name="IndChange" type="java.lang.String"><![CDATA[I]]></Field>
	<Field name="IndHiveCluster" type="java.lang.String">null</Field>
	<Field name="IndHivePartition" type="java.lang.String">null</Field>
	<Field name="IndHiveSort" type="java.lang.String">null</Field>
	<Field name="IndIn" type="java.lang.String">null</Field>
	<Field name="IndOut" type="java.lang.String">null</Field>
	<Field name="IndWrite" type="java.lang.String"><![CDATA[1]]></Field>
	<Field name="IndWsInsert" type="java.lang.String"><![CDATA[1]]></Field>
	<Field name="IndWsSelect" type="java.lang.String"><![CDATA[1]]></Field>
	<Field name="IndWsUpdate" type="java.lang.String"><![CDATA[1]]></Field>
	<Field name="IntVersion" type="com.sunopsis.sql.DbInt"><![CDATA[1]]></Field>
	<Field name="ICol" type="com.sunopsis.sql.DbInt"><![CDATA[28499]]></Field>
	<Field name="ISrcCol" type="com.sunopsis.sql.DbInt"><![CDATA[null]]></Field>
	<Field name="ITable" type="com.sunopsis.sql.DbInt"><![CDATA[597]]></Field>
	<Field name="ITxtColDesc" type="com.sunopsis.sql.DbInt"><![CDATA[null]]></Field>
	<Field name="LastDate" type="java.sql.Timestamp"><![CDATA[2017-02-17 15:27:02.0]]></Field>
	<Field name="LastUser" type="java.lang.String"><![CDATA[SUPERVISOR]]></Field>
	<Field name="Longc" type="com.sunopsis.sql.DbInt"><![CDATA[50]]></Field>
	<Field name="Pos" type="com.sunopsis.sql.DbInt"><![CDATA[4]]></Field>
	<Field name="RecCodeList" type="java.lang.String">null</Field>
	<Field name="Scalec" type="com.sunopsis.sql.DbInt"><![CDATA[null]]></Field>
	<Field name="ScdColType" type="java.lang.String">null</Field>
	<Field name="SourceDt" type="java.lang.String"><![CDATA[VARCHAR2]]></Field>
</Object>
<Object class="com.sunopsis.dwg.dbobj.SnpCol">
		<Field name="Bytes" type="com.sunopsis.sql.DbInt"><![CDATA[0]]></Field>
	<Field name="CheckFlow" type="java.lang.String"><![CDATA[1]]></Field>
	<Field name="CheckStat" type="java.lang.String"><![CDATA[0]]></Field>
	<Field name="ColDecSep" type="java.lang.String">null</Field>
	<Field name="ColFormat" type="java.lang.String">null</Field>
	<Field name="ColHeading" type="java.lang.String"><![CDATA[ON_HOLD_SUB_STATE]]></Field>
	<Field name="ColMandatory" type="java.lang.String"><![CDATA[0]]></Field>
	<Field name="ColName" type="java.lang.String"><![CDATA[ON_HOLD_SUB_STATE]]></Field>
	<Field name="ColNullIfErr" type="java.lang.String">null</Field>
	<Field name="DataFormat" type="java.lang.String">null</Field>
	<Field name="DefValue" type="java.lang.String">null</Field>
	<Field name="ExtVersion" type="java.lang.String">null</Field>
	<Field name="FilePos" type="com.sunopsis.sql.DbInt"><![CDATA[null]]></Field>
	<Field name="FirstDate" type="java.sql.Timestamp"><![CDATA[2017-02-17 15:27:01.0]]></Field>
	<Field name="FirstUser" type="java.lang.String"><![CDATA[SUPERVISOR]]></Field>
	<Field name="GlobalId" type="java.lang.String"><![CDATA[6fa04146-c185-4889-a829-e5df584ba098]]></Field>
	<Field name="HbaseEncoding" type="java.lang.String">null</Field>
	<Field name="HiveSortbyPos" type="com.sunopsis.sql.DbInt"><![CDATA[null]]></Field>
	<Field name="IndChange" type="java.lang.String"><![CDATA[I]]></Field>
	<Field name="IndHiveCluster" type="java.lang.String">null</Field>
	<Field name="IndHivePartition" type="java.lang.String">null</Field>
	<Field name="IndHiveSort" type="java.lang.String">null</Field>
	<Field name="IndIn" type="java.lang.String">null</Field>
	<Field name="IndOut" type="java.lang.String">null</Field>
	<Field name="IndWrite" type="java.lang.String"><![CDATA[1]]></Field>
	<Field name="IndWsInsert" type="java.lang.String"><![CDATA[1]]></Field>
	<Field name="IndWsSelect" type="java.lang.String"><![CDATA[1]]></Field>
	<Field name="IndWsUpdate" type="java.lang.String"><![CDATA[1]]></Field>
	<Field name="IntVersion" type="com.sunopsis.sql.DbInt"><![CDATA[1]]></Field>
	<Field name="ICol" type="com.sunopsis.sql.DbInt"><![CDATA[28486]]></Field>
	<Field name="ISrcCol" type="com.sunopsis.sql.DbInt"><![CDATA[null]]></Field>
	<Field name="ITable" type="com.sunopsis.sql.DbInt"><![CDATA[597]]></Field>
	<Field name="ITxtColDesc" type="com.sunopsis.sql.DbInt"><![CDATA[null]]></Field>
	<Field name="LastDate" type="java.sql.Timestamp"><![CDATA[2017-02-17 15:27:01.0]]></Field>
	<Field name="LastUser" type="java.lang.String"><![CDATA[SUPERVISOR]]></Field>
	<Field name="Longc" type="com.sunopsis.sql.DbInt"><![CDATA[50]]></Field>
	<Field name="Pos" type="com.sunopsis.sql.DbInt"><![CDATA[5]]></Field>
	<Field name="RecCodeList" type="java.lang.String">null</Field>
	<Field name="Scalec" type="com.sunopsis.sql.DbInt"><![CDATA[null]]></Field>
	<Field name="ScdColType" type="java.lang.String">null</Field>
	<Field name="SourceDt" type="java.lang.String"><![CDATA[VARCHAR2]]></Field>
</Object>
<Object class="com.sunopsis.dwg.dbobj.SnpCol">
		<Field name="Bytes" type="com.sunopsis.sql.DbInt"><![CDATA[0]]></Field>
	<Field name="CheckFlow" type="java.lang.String"><![CDATA[1]]></Field>
	<Field name="CheckStat" type="java.lang.String"><![CDATA[0]]></Field>
	<Field name="ColDecSep" type="java.lang.String">null</Field>
	<Field name="ColFormat" type="java.lang.String">null</Field>
	<Field name="ColHeading" type="java.lang.String"><![CDATA[REPORTED_CI]]></Field>
	<Field name="ColMandatory" type="java.lang.String"><![CDATA[0]]></Field>
	<Field name="ColName" type="java.lang.String"><![CDATA[REPORTED_CI]]></Field>
	<Field name="ColNullIfErr" type="java.lang.String">null</Field>
	<Field name="DataFormat" type="java.lang.String">null</Field>
	<Field name="DefValue" type="java.lang.String">null</Field>
	<Field name="ExtVersion" type="java.lang.String">null</Field>
	<Field name="FilePos" type="com.sunopsis.sql.DbInt"><![CDATA[null]]></Field>
	<Field name="FirstDate" type="java.sql.Timestamp"><![CDATA[2017-02-17 15:27:02.0]]></Field>
	<Field name="FirstUser" type="java.lang.String"><![CDATA[SUPERVISOR]]></Field>
	<Field name="GlobalId" type="java.lang.String"><![CDATA[1f00bf4a-07c0-4e56-a262-4e46b5a16f3c]]></Field>
	<Field name="HbaseEncoding" type="java.lang.String">null</Field>
	<Field name="HiveSortbyPos" type="com.sunopsis.sql.DbInt"><![CDATA[null]]></Field>
	<Field name="IndChange" type="java.lang.String"><![CDATA[I]]></Field>
	<Field name="IndHiveCluster" type="java.lang.String">null</Field>
	<Field name="IndHivePartition" type="java.lang.String">null</Field>
	<Field name="IndHiveSort" type="java.lang.String">null</Field>
	<Field name="IndIn" type="java.lang.String">null</Field>
	<Field name="IndOut" type="java.lang.String">null</Field>
	<Field name="IndWrite" type="java.lang.String"><![CDATA[1]]></Field>
	<Field name="IndWsInsert" type="java.lang.String"><![CDATA[1]]></Field>
	<Field name="IndWsSelect" type="java.lang.String"><![CDATA[1]]></Field>
	<Field name="IndWsUpdate" type="java.lang.String"><![CDATA[1]]></Field>
	<Field name="IntVersion" type="com.sunopsis.sql.DbInt"><![CDATA[1]]></Field>
	<Field name="ICol" type="com.sunopsis.sql.DbInt"><![CDATA[28491]]></Field>
	<Field name="ISrcCol" type="com.sunopsis.sql.DbInt"><![CDATA[null]]></Field>
	<Field name="ITable" type="com.sunopsis.sql.DbInt"><![CDATA[597]]></Field>
	<Field name="ITxtColDesc" type="com.sunopsis.sql.DbInt"><![CDATA[null]]></Field>
	<Field name="LastDate" type="java.sql.Timestamp"><![CDATA[2017-02-17 15:27:02.0]]></Field>
	<Field name="LastUser" type="java.lang.String"><![CDATA[SUPERVISOR]]></Field>
	<Field name="Longc" type="com.sunopsis.sql.DbInt"><![CDATA[200]]></Field>
	<Field name="Pos" type="com.sunopsis.sql.DbInt"><![CDATA[6]]></Field>
	<Field name="RecCodeList" type="java.lang.String">null</Field>
	<Field name="Scalec" type="com.sunopsis.sql.DbInt"><![CDATA[null]]></Field>
	<Field name="ScdColType" type="java.lang.String">null</Field>
	<Field name="SourceDt" type="java.lang.String"><![CDATA[VARCHAR2]]></Field>
</Object>
<Object class="com.sunopsis.dwg.dbobj.SnpCol">
		<Field name="Bytes" type="com.sunopsis.sql.DbInt"><![CDATA[0]]></Field>
	<Field name="CheckFlow" type="java.lang.String"><![CDATA[1]]></Field>
	<Field name="CheckStat" type="java.lang.String"><![CDATA[0]]></Field>
	<Field name="ColDecSep" type="java.lang.String">null</Field>
	<Field name="ColFormat" type="java.lang.String">null</Field>
	<Field name="ColHeading" type="java.lang.String"><![CDATA[ASSIGNMENT_GROUP]]></Field>
	<Field name="ColMandatory" type="java.lang.String"><![CDATA[0]]></Field>
	<Field name="ColName" type="java.lang.String"><![CDATA[ASSIGNMENT_GROUP]]></Field>
	<Field name="ColNullIfErr" type="java.lang.String">null</Field>
	<Field name="DataFormat" type="java.lang.String">null</Field>
	<Field name="DefValue" type="java.lang.String">null</Field>
	<Field name="ExtVersion" type="java.lang.String">null</Field>
	<Field name="FilePos" type="com.sunopsis.sql.DbInt"><![CDATA[null]]></Field>
	<Field name="FirstDate" type="java.sql.Timestamp"><![CDATA[2017-02-17 15:27:01.0]]></Field>
	<Field name="FirstUser" type="java.lang.String"><![CDATA[SUPERVISOR]]></Field>
	<Field name="GlobalId" type="java.lang.String"><![CDATA[38d98265-7745-4a59-b757-da9dd37f20b6]]></Field>
	<Field name="HbaseEncoding" type="java.lang.String">null</Field>
	<Field name="HiveSortbyPos" type="com.sunopsis.sql.DbInt"><![CDATA[null]]></Field>
	<Field name="IndChange" type="java.lang.String"><![CDATA[I]]></Field>
	<Field name="IndHiveCluster" type="java.lang.String">null</Field>
	<Field name="IndHivePartition" type="java.lang.String">null</Field>
	<Field name="IndHiveSort" type="java.lang.String">null</Field>
	<Field name="IndIn" type="java.lang.String">null</Field>
	<Field name="IndOut" type="java.lang.String">null</Field>
	<Field name="IndWrite" type="java.lang.String"><![CDATA[1]]></Field>
	<Field name="IndWsInsert" type="java.lang.String"><![CDATA[1]]></Field>
	<Field name="IndWsSelect" type="java.lang.String"><![CDATA[1]]></Field>
	<Field name="IndWsUpdate" type="java.lang.String"><![CDATA[1]]></Field>
	<Field name="IntVersion" type="com.sunopsis.sql.DbInt"><![CDATA[1]]></Field>
	<Field name="ICol" type="com.sunopsis.sql.DbInt"><![CDATA[28477]]></Field>
	<Field name="ISrcCol" type="com.sunopsis.sql.DbInt"><![CDATA[null]]></Field>
	<Field name="ITable" type="com.sunopsis.sql.DbInt"><![CDATA[597]]></Field>
	<Field name="ITxtColDesc" type="com.sunopsis.sql.DbInt"><![CDATA[null]]></Field>
	<Field name="LastDate" type="java.sql.Timestamp"><![CDATA[2017-02-17 15:27:01.0]]></Field>
	<Field name="LastUser" type="java.lang.String"><![CDATA[SUPERVISOR]]></Field>
	<Field name="Longc" type="com.sunopsis.sql.DbInt"><![CDATA[100]]></Field>
	<Field name="Pos" type="com.sunopsis.sql.DbInt"><![CDATA[7]]></Field>
	<Field name="RecCodeList" type="java.lang.String">null</Field>
	<Field name="Scalec" type="com.sunopsis.sql.DbInt"><![CDATA[null]]></Field>
	<Field name="ScdColType" type="java.lang.String">null</Field>
	<Field name="SourceDt" type="java.lang.String"><![CDATA[VARCHAR2]]></Field>
</Object>
<Object class="com.sunopsis.dwg.dbobj.SnpCol">
		<Field name="Bytes" type="com.sunopsis.sql.DbInt"><![CDATA[0]]></Field>
	<Field name="CheckFlow" type="java.lang.String"><![CDATA[1]]></Field>
	<Field name="CheckStat" type="java.lang.String"><![CDATA[0]]></Field>
	<Field name="ColDecSep" type="java.lang.String">null</Field>
	<Field name="ColFormat" type="java.lang.String">null</Field>
	<Field name="ColHeading" type="java.lang.String"><![CDATA[ASSIGNED_TO]]></Field>
	<Field name="ColMandatory" type="java.lang.String"><![CDATA[0]]></Field>
	<Field name="ColName" type="java.lang.String"><![CDATA[ASSIGNED_TO]]></Field>
	<Field name="ColNullIfErr" type="java.lang.String">null</Field>
	<Field name="DataFormat" type="java.lang.String">null</Field>
	<Field name="DefValue" type="java.lang.String">null</Field>
	<Field name="ExtVersion" type="java.lang.String">null</Field>
	<Field name="FilePos" type="com.sunopsis.sql.DbInt"><![CDATA[null]]></Field>
	<Field name="FirstDate" type="java.sql.Timestamp"><![CDATA[2017-02-17 15:27:01.0]]></Field>
	<Field name="FirstUser" type="java.lang.String"><![CDATA[SUPERVISOR]]></Field>
	<Field name="GlobalId" type="java.lang.String"><![CDATA[ce43741c-4ef1-4f2b-bac1-ccd340914c94]]></Field>
	<Field name="HbaseEncoding" type="java.lang.String">null</Field>
	<Field name="HiveSortbyPos" type="com.sunopsis.sql.DbInt"><![CDATA[null]]></Field>
	<Field name="IndChange" type="java.lang.String"><![CDATA[I]]></Field>
	<Field name="IndHiveCluster" type="java.lang.String">null</Field>
	<Field name="IndHivePartition" type="java.lang.String">null</Field>
	<Field name="IndHiveSort" type="java.lang.String">null</Field>
	<Field name="IndIn" type="java.lang.String">null</Field>
	<Field name="IndOut" type="java.lang.String">null</Field>
	<Field name="IndWrite" type="java.lang.String"><![CDATA[1]]></Field>
	<Field name="IndWsInsert" type="java.lang.String"><![CDATA[1]]></Field>
	<Field name="IndWsSelect" type="java.lang.String"><![CDATA[1]]></Field>
	<Field name="IndWsUpdate" type="java.lang.String"><![CDATA[1]]></Field>
	<Field name="IntVersion" type="com.sunopsis.sql.DbInt"><![CDATA[1]]></Field>
	<Field name="ICol" type="com.sunopsis.sql.DbInt"><![CDATA[28476]]></Field>
	<Field name="ISrcCol" type="com.sunopsis.sql.DbInt"><![CDATA[null]]></Field>
	<Field name="ITable" type="com.sunopsis.sql.DbInt"><![CDATA[597]]></Field>
	<Field name="ITxtColDesc" type="com.sunopsis.sql.DbInt"><![CDATA[null]]></Field>
	<Field name="LastDate" type="java.sql.Timestamp"><![CDATA[2017-02-17 15:27:01.0]]></Field>
	<Field name="LastUser" type="java.lang.String"><![CDATA[SUPERVISOR]]></Field>
	<Field name="Longc" type="com.sunopsis.sql.DbInt"><![CDATA[50]]></Field>
	<Field name="Pos" type="com.sunopsis.sql.DbInt"><![CDATA[8]]></Field>
	<Field name="RecCodeList" type="java.lang.String">null</Field>
	<Field name="Scalec" type="com.sunopsis.sql.DbInt"><![CDATA[null]]></Field>
	<Field name="ScdColType" type="java.lang.String">null</Field>
	<Field name="SourceDt" type="java.lang.String"><![CDATA[VARCHAR2]]></Field>
</Object>
<Object class="com.sunopsis.dwg.dbobj.SnpCol">
		<Field name="Bytes" type="com.sunopsis.sql.DbInt"><![CDATA[0]]></Field>
	<Field name="CheckFlow" type="java.lang.String"><![CDATA[1]]></Field>
	<Field name="CheckStat" type="java.lang.String"><![CDATA[0]]></Field>
	<Field name="ColDecSep" type="java.lang.String">null</Field>
	<Field name="ColFormat" type="java.lang.String">null</Field>
	<Field name="ColHeading" type="java.lang.String"><![CDATA[RESOLVED]]></Field>
	<Field name="ColMandatory" type="java.lang.String"><![CDATA[0]]></Field>
	<Field name="ColName" type="java.lang.String"><![CDATA[RESOLVED]]></Field>
	<Field name="ColNullIfErr" type="java.lang.String">null</Field>
	<Field name="DataFormat" type="java.lang.String">null</Field>
	<Field name="DefValue" type="java.lang.String">null</Field>
	<Field name="ExtVersion" type="java.lang.String">null</Field>
	<Field name="FilePos" type="com.sunopsis.sql.DbInt"><![CDATA[null]]></Field>
	<Field name="FirstDate" type="java.sql.Timestamp"><![CDATA[2017-02-17 15:27:02.0]]></Field>
	<Field name="FirstUser" type="java.lang.String"><![CDATA[SUPERVISOR]]></Field>
	<Field name="GlobalId" type="java.lang.String"><![CDATA[4e0c6fbe-c1eb-4732-a2e3-951235662737]]></Field>
	<Field name="HbaseEncoding" type="java.lang.String">null</Field>
	<Field name="HiveSortbyPos" type="com.sunopsis.sql.DbInt"><![CDATA[null]]></Field>
	<Field name="IndChange" type="java.lang.String"><![CDATA[I]]></Field>
	<Field name="IndHiveCluster" type="java.lang.String">null</Field>
	<Field name="IndHivePartition" type="java.lang.String">null</Field>
	<Field name="IndHiveSort" type="java.lang.String">null</Field>
	<Field name="IndIn" type="java.lang.String">null</Field>
	<Field name="IndOut" type="java.lang.String">null</Field>
	<Field name="IndWrite" type="java.lang.String"><![CDATA[1]]></Field>
	<Field name="IndWsInsert" type="java.lang.String"><![CDATA[1]]></Field>
	<Field name="IndWsSelect" type="java.lang.String"><![CDATA[1]]></Field>
	<Field name="IndWsUpdate" type="java.lang.String"><![CDATA[1]]></Field>
	<Field name="IntVersion" type="com.sunopsis.sql.DbInt"><![CDATA[1]]></Field>
	<Field name="ICol" type="com.sunopsis.sql.DbInt"><![CDATA[28492]]></Field>
	<Field name="ISrcCol" type="com.sunopsis.sql.DbInt"><![CDATA[null]]></Field>
	<Field name="ITable" type="com.sunopsis.sql.DbInt"><![CDATA[597]]></Field>
	<Field name="ITxtColDesc" type="com.sunopsis.sql.DbInt"><![CDATA[null]]></Field>
	<Field name="LastDate" type="java.sql.Timestamp"><![CDATA[2017-02-17 15:27:02.0]]></Field>
	<Field name="LastUser" type="java.lang.String"><![CDATA[SUPERVISOR]]></Field>
	<Field name="Longc" type="com.sunopsis.sql.DbInt"><![CDATA[null]]></Field>
	<Field name="Pos" type="com.sunopsis.sql.DbInt"><![CDATA[9]]></Field>
	<Field name="RecCodeList" type="java.lang.String">null</Field>
	<Field name="Scalec" type="com.sunopsis.sql.DbInt"><![CDATA[null]]></Field>
	<Field name="ScdColType" type="java.lang.String">null</Field>
	<Field name="SourceDt" type="java.lang.String"><![CDATA[DATE]]></Field>
</Object>
<Object class="com.sunopsis.dwg.dbobj.SnpCol">
		<Field name="Bytes" type="com.sunopsis.sql.DbInt"><![CDATA[0]]></Field>
	<Field name="CheckFlow" type="java.lang.String"><![CDATA[1]]></Field>
	<Field name="CheckStat" type="java.lang.String"><![CDATA[0]]></Field>
	<Field name="ColDecSep" type="java.lang.String">null</Field>
	<Field name="ColFormat" type="java.lang.String">null</Field>
	<Field name="ColHeading" type="java.lang.String"><![CDATA[SHORT_DESCRIPTION]]></Field>
	<Field name="ColMandatory" type="java.lang.String"><![CDATA[0]]></Field>
	<Field name="ColName" type="java.lang.String"><![CDATA[SHORT_DESCRIPTION]]></Field>
	<Field name="ColNullIfErr" type="java.lang.String">null</Field>
	<Field name="DataFormat" type="java.lang.String">null</Field>
	<Field name="DefValue" type="java.lang.String">null</Field>
	<Field name="ExtVersion" type="java.lang.String">null</Field>
	<Field name="FilePos" type="com.sunopsis.sql.DbInt"><![CDATA[null]]></Field>
	<Field name="FirstDate" type="java.sql.Timestamp"><![CDATA[2017-02-17 15:27:02.0]]></Field>
	<Field name="FirstUser" type="java.lang.String"><![CDATA[SUPERVISOR]]></Field>
	<Field name="GlobalId" type="java.lang.String"><![CDATA[9638a319-87b3-4d8f-81bb-4fde6f5740d9]]></Field>
	<Field name="HbaseEncoding" type="java.lang.String">null</Field>
	<Field name="HiveSortbyPos" type="com.sunopsis.sql.DbInt"><![CDATA[null]]></Field>
	<Field name="IndChange" type="java.lang.String"><![CDATA[I]]></Field>
	<Field name="IndHiveCluster" type="java.lang.String">null</Field>
	<Field name="IndHivePartition" type="java.lang.String">null</Field>
	<Field name="IndHiveSort" type="java.lang.String">null</Field>
	<Field name="IndIn" type="java.lang.String">null</Field>
	<Field name="IndOut" type="java.lang.String">null</Field>
	<Field name="IndWrite" type="java.lang.String"><![CDATA[1]]></Field>
	<Field name="IndWsInsert" type="java.lang.String"><![CDATA[1]]></Field>
	<Field name="IndWsSelect" type="java.lang.String"><![CDATA[1]]></Field>
	<Field name="IndWsUpdate" type="java.lang.String"><![CDATA[1]]></Field>
	<Field name="IntVersion" type="com.sunopsis.sql.DbInt"><![CDATA[1]]></Field>
	<Field name="ICol" type="com.sunopsis.sql.DbInt"><![CDATA[28496]]></Field>
	<Field name="ISrcCol" type="com.sunopsis.sql.DbInt"><![CDATA[null]]></Field>
	<Field name="ITable" type="com.sunopsis.sql.DbInt"><![CDATA[597]]></Field>
	<Field name="ITxtColDesc" type="com.sunopsis.sql.DbInt"><![CDATA[null]]></Field>
	<Field name="LastDate" type="java.sql.Timestamp"><![CDATA[2017-02-17 15:27:02.0]]></Field>
	<Field name="LastUser" type="java.lang.String"><![CDATA[SUPERVISOR]]></Field>
	<Field name="Longc" type="com.sunopsis.sql.DbInt"><![CDATA[500]]></Field>
	<Field name="Pos" type="com.sunopsis.sql.DbInt"><![CDATA[10]]></Field>
	<Field name="RecCodeList" type="java.lang.String">null</Field>
	<Field name="Scalec" type="com.sunopsis.sql.DbInt"><![CDATA[null]]></Field>
	<Field name="ScdColType" type="java.lang.String">null</Field>
	<Field name="SourceDt" type="java.lang.String"><![CDATA[VARCHAR2]]></Field>
</Object>
<Object class="com.sunopsis.dwg.dbobj.SnpCol">
		<Field name="Bytes" type="com.sunopsis.sql.DbInt"><![CDATA[0]]></Field>
	<Field name="CheckFlow" type="java.lang.String"><![CDATA[1]]></Field>
	<Field name="CheckStat" type="java.lang.String"><![CDATA[0]]></Field>
	<Field name="ColDecSep" type="java.lang.String">null</Field>
	<Field name="ColFormat" type="java.lang.String">null</Field>
	<Field name="ColHeading" type="java.lang.String"><![CDATA[URGENCY]]></Field>
	<Field name="ColMandatory" type="java.lang.String"><![CDATA[0]]></Field>
	<Field name="ColName" type="java.lang.String"><![CDATA[URGENCY]]></Field>
	<Field name="ColNullIfErr" type="java.lang.String">null</Field>
	<Field name="DataFormat" type="java.lang.String">null</Field>
	<Field name="DefValue" type="java.lang.String">null</Field>
	<Field name="ExtVersion" type="java.lang.String">null</Field>
	<Field name="FilePos" type="com.sunopsis.sql.DbInt"><![CDATA[null]]></Field>
	<Field name="FirstDate" type="java.sql.Timestamp"><![CDATA[2017-02-17 15:27:02.0]]></Field>
	<Field name="FirstUser" type="java.lang.String"><![CDATA[SUPERVISOR]]></Field>
	<Field name="GlobalId" type="java.lang.String"><![CDATA[5ff6a551-d539-4499-aafb-6d89813efaac]]></Field>
	<Field name="HbaseEncoding" type="java.lang.String">null</Field>
	<Field name="HiveSortbyPos" type="com.sunopsis.sql.DbInt"><![CDATA[null]]></Field>
	<Field name="IndChange" type="java.lang.String"><![CDATA[I]]></Field>
	<Field name="IndHiveCluster" type="java.lang.String">null</Field>
	<Field name="IndHivePartition" type="java.lang.String">null</Field>
	<Field name="IndHiveSort" type="java.lang.String">null</Field>
	<Field name="IndIn" type="java.lang.String">null</Field>
	<Field name="IndOut" type="java.lang.String">null</Field>
	<Field name="IndWrite" type="java.lang.String"><![CDATA[1]]></Field>
	<Field name="IndWsInsert" type="java.lang.String"><![CDATA[1]]></Field>
	<Field name="IndWsSelect" type="java.lang.String"><![CDATA[1]]></Field>
	<Field name="IndWsUpdate" type="java.lang.String"><![CDATA[1]]></Field>
	<Field name="IntVersion" type="com.sunopsis.sql.DbInt"><![CDATA[1]]></Field>
	<Field name="ICol" type="com.sunopsis.sql.DbInt"><![CDATA[28501]]></Field>
	<Field name="ISrcCol" type="com.sunopsis.sql.DbInt"><![CDATA[null]]></Field>
	<Field name="ITable" type="com.sunopsis.sql.DbInt"><![CDATA[597]]></Field>
	<Field name="ITxtColDesc" type="com.sunopsis.sql.DbInt"><![CDATA[null]]></Field>
	<Field name="LastDate" type="java.sql.Timestamp"><![CDATA[2017-02-17 15:27:02.0]]></Field>
	<Field name="LastUser" type="java.lang.String"><![CDATA[SUPERVISOR]]></Field>
	<Field name="Longc" type="com.sunopsis.sql.DbInt"><![CDATA[50]]></Field>
	<Field name="Pos" type="com.sunopsis.sql.DbInt"><![CDATA[11]]></Field>
	<Field name="RecCodeList" type="java.lang.String">null</Field>
	<Field name="Scalec" type="com.sunopsis.sql.DbInt"><![CDATA[null]]></Field>
	<Field name="ScdColType" type="java.lang.String">null</Field>
	<Field name="SourceDt" type="java.lang.String"><![CDATA[VARCHAR2]]></Field>
</Object>
<Object class="com.sunopsis.dwg.dbobj.SnpCol">
		<Field name="Bytes" type="com.sunopsis.sql.DbInt"><![CDATA[0]]></Field>
	<Field name="CheckFlow" type="java.lang.String"><![CDATA[1]]></Field>
	<Field name="CheckStat" type="java.lang.String"><![CDATA[0]]></Field>
	<Field name="ColDecSep" type="java.lang.String">null</Field>
	<Field name="ColFormat" type="java.lang.String">null</Field>
	<Field name="ColHeading" type="java.lang.String"><![CDATA[PROBLEM]]></Field>
	<Field name="ColMandatory" type="java.lang.String"><![CDATA[0]]></Field>
	<Field name="ColName" type="java.lang.String"><![CDATA[PROBLEM]]></Field>
	<Field name="ColNullIfErr" type="java.lang.String">null</Field>
	<Field name="DataFormat" type="java.lang.String">null</Field>
	<Field name="DefValue" type="java.lang.String">null</Field>
	<Field name="ExtVersion" type="java.lang.String">null</Field>
	<Field name="FilePos" type="com.sunopsis.sql.DbInt"><![CDATA[null]]></Field>
	<Field name="FirstDate" type="java.sql.Timestamp"><![CDATA[2017-02-17 15:27:01.0]]></Field>
	<Field name="FirstUser" type="java.lang.String"><![CDATA[SUPERVISOR]]></Field>
	<Field name="GlobalId" type="java.lang.String"><![CDATA[afb8271e-f981-4359-9106-a984789eebcd]]></Field>
	<Field name="HbaseEncoding" type="java.lang.String">null</Field>
	<Field name="HiveSortbyPos" type="com.sunopsis.sql.DbInt"><![CDATA[null]]></Field>
	<Field name="IndChange" type="java.lang.String"><![CDATA[I]]></Field>
	<Field name="IndHiveCluster" type="java.lang.String">null</Field>
	<Field name="IndHivePartition" type="java.lang.String">null</Field>
	<Field name="IndHiveSort" type="java.lang.String">null</Field>
	<Field name="IndIn" type="java.lang.String">null</Field>
	<Field name="IndOut" type="java.lang.String">null</Field>
	<Field name="IndWrite" type="java.lang.String"><![CDATA[1]]></Field>
	<Field name="IndWsInsert" type="java.lang.String"><![CDATA[1]]></Field>
	<Field name="IndWsSelect" type="java.lang.String"><![CDATA[1]]></Field>
	<Field name="IndWsUpdate" type="java.lang.String"><![CDATA[1]]></Field>
	<Field name="IntVersion" type="com.sunopsis.sql.DbInt"><![CDATA[1]]></Field>
	<Field name="ICol" type="com.sunopsis.sql.DbInt"><![CDATA[28488]]></Field>
	<Field name="ISrcCol" type="com.sunopsis.sql.DbInt"><![CDATA[null]]></Field>
	<Field name="ITable" type="com.sunopsis.sql.DbInt"><![CDATA[597]]></Field>
	<Field name="ITxtColDesc" type="com.sunopsis.sql.DbInt"><![CDATA[null]]></Field>
	<Field name="LastDate" type="java.sql.Timestamp"><![CDATA[2017-02-17 15:27:01.0]]></Field>
	<Field name="LastUser" type="java.lang.String"><![CDATA[SUPERVISOR]]></Field>
	<Field name="Longc" type="com.sunopsis.sql.DbInt"><![CDATA[50]]></Field>
	<Field name="Pos" type="com.sunopsis.sql.DbInt"><![CDATA[12]]></Field>
	<Field name="RecCodeList" type="java.lang.String">null</Field>
	<Field name="Scalec" type="com.sunopsis.sql.DbInt"><![CDATA[null]]></Field>
	<Field name="ScdColType" type="java.lang.String">null</Field>
	<Field name="SourceDt" type="java.lang.String"><![CDATA[VARCHAR2]]></Field>
</Object>
<Object class="com.sunopsis.dwg.dbobj.SnpCol">
		<Field name="Bytes" type="com.sunopsis.sql.DbInt"><![CDATA[0]]></Field>
	<Field name="CheckFlow" type="java.lang.String"><![CDATA[1]]></Field>
	<Field name="CheckStat" type="java.lang.String"><![CDATA[0]]></Field>
	<Field name="ColDecSep" type="java.lang.String">null</Field>
	<Field name="ColFormat" type="java.lang.String">null</Field>
	<Field name="ColHeading" type="java.lang.String"><![CDATA[PRIORITY]]></Field>
	<Field name="ColMandatory" type="java.lang.String"><![CDATA[0]]></Field>
	<Field name="ColName" type="java.lang.String"><![CDATA[PRIORITY]]></Field>
	<Field name="ColNullIfErr" type="java.lang.String">null</Field>
	<Field name="DataFormat" type="java.lang.String">null</Field>
	<Field name="DefValue" type="java.lang.String">null</Field>
	<Field name="ExtVersion" type="java.lang.String">null</Field>
	<Field name="FilePos" type="com.sunopsis.sql.DbInt"><![CDATA[null]]></Field>
	<Field name="FirstDate" type="java.sql.Timestamp"><![CDATA[2017-02-17 15:27:01.0]]></Field>
	<Field name="FirstUser" type="java.lang.String"><![CDATA[SUPERVISOR]]></Field>
	<Field name="GlobalId" type="java.lang.String"><![CDATA[069caaa1-5cae-43b9-82a1-964efb050a5a]]></Field>
	<Field name="HbaseEncoding" type="java.lang.String">null</Field>
	<Field name="HiveSortbyPos" type="com.sunopsis.sql.DbInt"><![CDATA[null]]></Field>
	<Field name="IndChange" type="java.lang.String"><![CDATA[I]]></Field>
	<Field name="IndHiveCluster" type="java.lang.String">null</Field>
	<Field name="IndHivePartition" type="java.lang.String">null</Field>
	<Field name="IndHiveSort" type="java.lang.String">null</Field>
	<Field name="IndIn" type="java.lang.String">null</Field>
	<Field name="IndOut" type="java.lang.String">null</Field>
	<Field name="IndWrite" type="java.lang.String"><![CDATA[1]]></Field>
	<Field name="IndWsInsert" type="java.lang.String"><![CDATA[1]]></Field>
	<Field name="IndWsSelect" type="java.lang.String"><![CDATA[1]]></Field>
	<Field name="IndWsUpdate" type="java.lang.String"><![CDATA[1]]></Field>
	<Field name="IntVersion" type="com.sunopsis.sql.DbInt"><![CDATA[1]]></Field>
	<Field name="ICol" type="com.sunopsis.sql.DbInt"><![CDATA[28487]]></Field>
	<Field name="ISrcCol" type="com.sunopsis.sql.DbInt"><![CDATA[null]]></Field>
	<Field name="ITable" type="com.sunopsis.sql.DbInt"><![CDATA[597]]></Field>
	<Field name="ITxtColDesc" type="com.sunopsis.sql.DbInt"><![CDATA[null]]></Field>
	<Field name="LastDate" type="java.sql.Timestamp"><![CDATA[2017-02-17 15:27:01.0]]></Field>
	<Field name="LastUser" type="java.lang.String"><![CDATA[SUPERVISOR]]></Field>
	<Field name="Longc" type="com.sunopsis.sql.DbInt"><![CDATA[50]]></Field>
	<Field name="Pos" type="com.sunopsis.sql.DbInt"><![CDATA[13]]></Field>
	<Field name="RecCodeList" type="java.lang.String">null</Field>
	<Field name="Scalec" type="com.sunopsis.sql.DbInt"><![CDATA[null]]></Field>
	<Field name="ScdColType" type="java.lang.String">null</Field>
	<Field name="SourceDt" type="java.lang.String"><![CDATA[VARCHAR2]]></Field>
</Object>
<Object class="com.sunopsis.dwg.dbobj.SnpCol">
		<Field name="Bytes" type="com.sunopsis.sql.DbInt"><![CDATA[0]]></Field>
	<Field name="CheckFlow" type="java.lang.String"><![CDATA[1]]></Field>
	<Field name="CheckStat" type="java.lang.String"><![CDATA[0]]></Field>
	<Field name="ColDecSep" type="java.lang.String">null</Field>
	<Field name="ColFormat" type="java.lang.String">null</Field>
	<Field name="ColHeading" type="java.lang.String"><![CDATA[LAST_UPDATED]]></Field>
	<Field name="ColMandatory" type="java.lang.String"><![CDATA[1]]></Field>
	<Field name="ColName" type="java.lang.String"><![CDATA[LAST_UPDATED]]></Field>
	<Field name="ColNullIfErr" type="java.lang.String">null</Field>
	<Field name="DataFormat" type="java.lang.String">null</Field>
	<Field name="DefValue" type="java.lang.String">null</Field>
	<Field name="ExtVersion" type="java.lang.String">null</Field>
	<Field name="FilePos" type="com.sunopsis.sql.DbInt"><![CDATA[null]]></Field>
	<Field name="FirstDate" type="java.sql.Timestamp"><![CDATA[2017-02-17 15:27:01.0]]></Field>
	<Field name="FirstUser" type="java.lang.String"><![CDATA[SUPERVISOR]]></Field>
	<Field name="GlobalId" type="java.lang.String"><![CDATA[fdc29c74-071c-4216-a279-6a59a2a89778]]></Field>
	<Field name="HbaseEncoding" type="java.lang.String">null</Field>
	<Field name="HiveSortbyPos" type="com.sunopsis.sql.DbInt"><![CDATA[null]]></Field>
	<Field name="IndChange" type="java.lang.String"><![CDATA[I]]></Field>
	<Field name="IndHiveCluster" type="java.lang.String">null</Field>
	<Field name="IndHivePartition" type="java.lang.String">null</Field>
	<Field name="IndHiveSort" type="java.lang.String">null</Field>
	<Field name="IndIn" type="java.lang.String">null</Field>
	<Field name="IndOut" type="java.lang.String">null</Field>
	<Field name="IndWrite" type="java.lang.String"><![CDATA[1]]></Field>
	<Field name="IndWsInsert" type="java.lang.String"><![CDATA[1]]></Field>
	<Field name="IndWsSelect" type="java.lang.String"><![CDATA[1]]></Field>
	<Field name="IndWsUpdate" type="java.lang.String"><![CDATA[1]]></Field>
	<Field name="IntVersion" type="com.sunopsis.sql.DbInt"><![CDATA[1]]></Field>
	<Field name="ICol" type="com.sunopsis.sql.DbInt"><![CDATA[28485]]></Field>
	<Field name="ISrcCol" type="com.sunopsis.sql.DbInt"><![CDATA[null]]></Field>
	<Field name="ITable" type="com.sunopsis.sql.DbInt"><![CDATA[597]]></Field>
	<Field name="ITxtColDesc" type="com.sunopsis.sql.DbInt"><![CDATA[null]]></Field>
	<Field name="LastDate" type="java.sql.Timestamp"><![CDATA[2017-02-17 15:27:01.0]]></Field>
	<Field name="LastUser" type="java.lang.String"><![CDATA[SUPERVISOR]]></Field>
	<Field name="Longc" type="com.sunopsis.sql.DbInt"><![CDATA[null]]></Field>
	<Field name="Pos" type="com.sunopsis.sql.DbInt"><![CDATA[14]]></Field>
	<Field name="RecCodeList" type="java.lang.String">null</Field>
	<Field name="Scalec" type="com.sunopsis.sql.DbInt"><![CDATA[null]]></Field>
	<Field name="ScdColType" type="java.lang.String">null</Field>
	<Field name="SourceDt" type="java.lang.String"><![CDATA[DATE]]></Field>
</Object>
<Object class="com.sunopsis.dwg.dbobj.SnpCol">
		<Field name="Bytes" type="com.sunopsis.sql.DbInt"><![CDATA[0]]></Field>
	<Field name="CheckFlow" type="java.lang.String"><![CDATA[1]]></Field>
	<Field name="CheckStat" type="java.lang.String"><![CDATA[0]]></Field>
	<Field name="ColDecSep" type="java.lang.String">null</Field>
	<Field name="ColFormat" type="java.lang.String">null</Field>
	<Field name="ColHeading" type="java.lang.String"><![CDATA[ESCALATION]]></Field>
	<Field name="ColMandatory" type="java.lang.String"><![CDATA[0]]></Field>
	<Field name="ColName" type="java.lang.String"><![CDATA[ESCALATION]]></Field>
	<Field name="ColNullIfErr" type="java.lang.String">null</Field>
	<Field name="DataFormat" type="java.lang.String">null</Field>
	<Field name="DefValue" type="java.lang.String">null</Field>
	<Field name="ExtVersion" type="java.lang.String">null</Field>
	<Field name="FilePos" type="com.sunopsis.sql.DbInt"><![CDATA[null]]></Field>
	<Field name="FirstDate" type="java.sql.Timestamp"><![CDATA[2017-02-17 15:27:01.0]]></Field>
	<Field name="FirstUser" type="java.lang.String"><![CDATA[SUPERVISOR]]></Field>
	<Field name="GlobalId" type="java.lang.String"><![CDATA[89e4f009-8fe2-4ce6-970d-3c393503b329]]></Field>
	<Field name="HbaseEncoding" type="java.lang.String">null</Field>
	<Field name="HiveSortbyPos" type="com.sunopsis.sql.DbInt"><![CDATA[null]]></Field>
	<Field name="IndChange" type="java.lang.String"><![CDATA[I]]></Field>
	<Field name="IndHiveCluster" type="java.lang.String">null</Field>
	<Field name="IndHivePartition" type="java.lang.String">null</Field>
	<Field name="IndHiveSort" type="java.lang.String">null</Field>
	<Field name="IndIn" type="java.lang.String">null</Field>
	<Field name="IndOut" type="java.lang.String">null</Field>
	<Field name="IndWrite" type="java.lang.String"><![CDATA[1]]></Field>
	<Field name="IndWsInsert" type="java.lang.String"><![CDATA[1]]></Field>
	<Field name="IndWsSelect" type="java.lang.String"><![CDATA[1]]></Field>
	<Field name="IndWsUpdate" type="java.lang.String"><![CDATA[1]]></Field>
	<Field name="IntVersion" type="com.sunopsis.sql.DbInt"><![CDATA[1]]></Field>
	<Field name="ICol" type="com.sunopsis.sql.DbInt"><![CDATA[28483]]></Field>
	<Field name="ISrcCol" type="com.sunopsis.sql.DbInt"><![CDATA[null]]></Field>
	<Field name="ITable" type="com.sunopsis.sql.DbInt"><![CDATA[597]]></Field>
	<Field name="ITxtColDesc" type="com.sunopsis.sql.DbInt"><![CDATA[null]]></Field>
	<Field name="LastDate" type="java.sql.Timestamp"><![CDATA[2017-02-17 15:27:01.0]]></Field>
	<Field name="LastUser" type="java.lang.String"><![CDATA[SUPERVISOR]]></Field>
	<Field name="Longc" type="com.sunopsis.sql.DbInt"><![CDATA[500]]></Field>
	<Field name="Pos" type="com.sunopsis.sql.DbInt"><![CDATA[15]]></Field>
	<Field name="RecCodeList" type="java.lang.String">null</Field>
	<Field name="Scalec" type="com.sunopsis.sql.DbInt"><![CDATA[null]]></Field>
	<Field name="ScdColType" type="java.lang.String">null</Field>
	<Field name="SourceDt" type="java.lang.String"><![CDATA[VARCHAR2]]></Field>
</Object>
<Object class="com.sunopsis.dwg.dbobj.SnpCol">
		<Field name="Bytes" type="com.sunopsis.sql.DbInt"><![CDATA[0]]></Field>
	<Field name="CheckFlow" type="java.lang.String"><![CDATA[1]]></Field>
	<Field name="CheckStat" type="java.lang.String"><![CDATA[0]]></Field>
	<Field name="ColDecSep" type="java.lang.String">null</Field>
	<Field name="ColFormat" type="java.lang.String">null</Field>
	<Field name="ColHeading" type="java.lang.String"><![CDATA[DURATION]]></Field>
	<Field name="ColMandatory" type="java.lang.String"><![CDATA[0]]></Field>
	<Field name="ColName" type="java.lang.String"><![CDATA[DURATION]]></Field>
	<Field name="ColNullIfErr" type="java.lang.String">null</Field>
	<Field name="DataFormat" type="java.lang.String">null</Field>
	<Field name="DefValue" type="java.lang.String">null</Field>
	<Field name="ExtVersion" type="java.lang.String">null</Field>
	<Field name="FilePos" type="com.sunopsis.sql.DbInt"><![CDATA[null]]></Field>
	<Field name="FirstDate" type="java.sql.Timestamp"><![CDATA[2017-02-17 15:27:01.0]]></Field>
	<Field name="FirstUser" type="java.lang.String"><![CDATA[SUPERVISOR]]></Field>
	<Field name="GlobalId" type="java.lang.String"><![CDATA[17df9757-dcc4-4c05-9d42-a33642ce9018]]></Field>
	<Field name="HbaseEncoding" type="java.lang.String">null</Field>
	<Field name="HiveSortbyPos" type="com.sunopsis.sql.DbInt"><![CDATA[null]]></Field>
	<Field name="IndChange" type="java.lang.String"><![CDATA[I]]></Field>
	<Field name="IndHiveCluster" type="java.lang.String">null</Field>
	<Field name="IndHivePartition" type="java.lang.String">null</Field>
	<Field name="IndHiveSort" type="java.lang.String">null</Field>
	<Field name="IndIn" type="java.lang.String">null</Field>
	<Field name="IndOut" type="java.lang.String">null</Field>
	<Field name="IndWrite" type="java.lang.String"><![CDATA[1]]></Field>
	<Field name="IndWsInsert" type="java.lang.String"><![CDATA[1]]></Field>
	<Field name="IndWsSelect" type="java.lang.String"><![CDATA[1]]></Field>
	<Field name="IndWsUpdate" type="java.lang.String"><![CDATA[1]]></Field>
	<Field name="IntVersion" type="com.sunopsis.sql.DbInt"><![CDATA[1]]></Field>
	<Field name="ICol" type="com.sunopsis.sql.DbInt"><![CDATA[28482]]></Field>
	<Field name="ISrcCol" type="com.sunopsis.sql.DbInt"><![CDATA[null]]></Field>
	<Field name="ITable" type="com.sunopsis.sql.DbInt"><![CDATA[597]]></Field>
	<Field name="ITxtColDesc" type="com.sunopsis.sql.DbInt"><![CDATA[null]]></Field>
	<Field name="LastDate" type="java.sql.Timestamp"><![CDATA[2017-02-17 15:27:01.0]]></Field>
	<Field name="LastUser" type="java.lang.String"><![CDATA[SUPERVISOR]]></Field>
	<Field name="Longc" type="com.sunopsis.sql.DbInt"><![CDATA[null]]></Field>
	<Field name="Pos" type="com.sunopsis.sql.DbInt"><![CDATA[16]]></Field>
	<Field name="RecCodeList" type="java.lang.String">null</Field>
	<Field name="Scalec" type="com.sunopsis.sql.DbInt"><![CDATA[null]]></Field>
	<Field name="ScdColType" type="java.lang.String">null</Field>
	<Field name="SourceDt" type="java.lang.String"><![CDATA[NUMBER]]></Field>
</Object>
<Object class="com.sunopsis.dwg.dbobj.SnpCol">
		<Field name="Bytes" type="com.sunopsis.sql.DbInt"><![CDATA[0]]></Field>
	<Field name="CheckFlow" type="java.lang.String"><![CDATA[1]]></Field>
	<Field name="CheckStat" type="java.lang.String"><![CDATA[0]]></Field>
	<Field name="ColDecSep" type="java.lang.String">null</Field>
	<Field name="ColFormat" type="java.lang.String">null</Field>
	<Field name="ColHeading" type="java.lang.String"><![CDATA[RESOLVING_COMPANY]]></Field>
	<Field name="ColMandatory" type="java.lang.String"><![CDATA[0]]></Field>
	<Field name="ColName" type="java.lang.String"><![CDATA[RESOLVING_COMPANY]]></Field>
	<Field name="ColNullIfErr" type="java.lang.String">null</Field>
	<Field name="DataFormat" type="java.lang.String">null</Field>
	<Field name="DefValue" type="java.lang.String">null</Field>
	<Field name="ExtVersion" type="java.lang.String">null</Field>
	<Field name="FilePos" type="com.sunopsis.sql.DbInt"><![CDATA[null]]></Field>
	<Field name="FirstDate" type="java.sql.Timestamp"><![CDATA[2017-02-17 15:27:02.0]]></Field>
	<Field name="FirstUser" type="java.lang.String"><![CDATA[SUPERVISOR]]></Field>
	<Field name="GlobalId" type="java.lang.String"><![CDATA[2703a8ee-4131-4ee7-9794-4fdd049101ba]]></Field>
	<Field name="HbaseEncoding" type="java.lang.String">null</Field>
	<Field name="HiveSortbyPos" type="com.sunopsis.sql.DbInt"><![CDATA[null]]></Field>
	<Field name="IndChange" type="java.lang.String"><![CDATA[I]]></Field>
	<Field name="IndHiveCluster" type="java.lang.String">null</Field>
	<Field name="IndHivePartition" type="java.lang.String">null</Field>
	<Field name="IndHiveSort" type="java.lang.String">null</Field>
	<Field name="IndIn" type="java.lang.String">null</Field>
	<Field name="IndOut" type="java.lang.String">null</Field>
	<Field name="IndWrite" type="java.lang.String"><![CDATA[1]]></Field>
	<Field name="IndWsInsert" type="java.lang.String"><![CDATA[1]]></Field>
	<Field name="IndWsSelect" type="java.lang.String"><![CDATA[1]]></Field>
	<Field name="IndWsUpdate" type="java.lang.String"><![CDATA[1]]></Field>
	<Field name="IntVersion" type="com.sunopsis.sql.DbInt"><![CDATA[1]]></Field>
	<Field name="ICol" type="com.sunopsis.sql.DbInt"><![CDATA[28494]]></Field>
	<Field name="ISrcCol" type="com.sunopsis.sql.DbInt"><![CDATA[null]]></Field>
	<Field name="ITable" type="com.sunopsis.sql.DbInt"><![CDATA[597]]></Field>
	<Field name="ITxtColDesc" type="com.sunopsis.sql.DbInt"><![CDATA[null]]></Field>
	<Field name="LastDate" type="java.sql.Timestamp"><![CDATA[2017-02-17 15:27:02.0]]></Field>
	<Field name="LastUser" type="java.lang.String"><![CDATA[SUPERVISOR]]></Field>
	<Field name="Longc" type="com.sunopsis.sql.DbInt"><![CDATA[150]]></Field>
	<Field name="Pos" type="com.sunopsis.sql.DbInt"><![CDATA[17]]></Field>
	<Field name="RecCodeList" type="java.lang.String">null</Field>
	<Field name="Scalec" type="com.sunopsis.sql.DbInt"><![CDATA[null]]></Field>
	<Field name="ScdColType" type="java.lang.String">null</Field>
	<Field name="SourceDt" type="java.lang.String"><![CDATA[VARCHAR2]]></Field>
</Object>
<Object class="com.sunopsis.dwg.dbobj.SnpCol">
		<Field name="Bytes" type="com.sunopsis.sql.DbInt"><![CDATA[0]]></Field>
	<Field name="CheckFlow" type="java.lang.String"><![CDATA[1]]></Field>
	<Field name="CheckStat" type="java.lang.String"><![CDATA[0]]></Field>
	<Field name="ColDecSep" type="java.lang.String">null</Field>
	<Field name="ColFormat" type="java.lang.String">null</Field>
	<Field name="ColHeading" type="java.lang.String"><![CDATA[CHILD_INCIDENTS]]></Field>
	<Field name="ColMandatory" type="java.lang.String"><![CDATA[0]]></Field>
	<Field name="ColName" type="java.lang.String"><![CDATA[CHILD_INCIDENTS]]></Field>
	<Field name="ColNullIfErr" type="java.lang.String">null</Field>
	<Field name="DataFormat" type="java.lang.String">null</Field>
	<Field name="DefValue" type="java.lang.String">null</Field>
	<Field name="ExtVersion" type="java.lang.String">null</Field>
	<Field name="FilePos" type="com.sunopsis.sql.DbInt"><![CDATA[null]]></Field>
	<Field name="FirstDate" type="java.sql.Timestamp"><![CDATA[2017-02-17 15:27:01.0]]></Field>
	<Field name="FirstUser" type="java.lang.String"><![CDATA[SUPERVISOR]]></Field>
	<Field name="GlobalId" type="java.lang.String"><![CDATA[32e35587-7c30-4dde-be0a-a8e9fa7f8ef3]]></Field>
	<Field name="HbaseEncoding" type="java.lang.String">null</Field>
	<Field name="HiveSortbyPos" type="com.sunopsis.sql.DbInt"><![CDATA[null]]></Field>
	<Field name="IndChange" type="java.lang.String"><![CDATA[I]]></Field>
	<Field name="IndHiveCluster" type="java.lang.String">null</Field>
	<Field name="IndHivePartition" type="java.lang.String">null</Field>
	<Field name="IndHiveSort" type="java.lang.String">null</Field>
	<Field name="IndIn" type="java.lang.String">null</Field>
	<Field name="IndOut" type="java.lang.String">null</Field>
	<Field name="IndWrite" type="java.lang.String"><![CDATA[1]]></Field>
	<Field name="IndWsInsert" type="java.lang.String"><![CDATA[1]]></Field>
	<Field name="IndWsSelect" type="java.lang.String"><![CDATA[1]]></Field>
	<Field name="IndWsUpdate" type="java.lang.String"><![CDATA[1]]></Field>
	<Field name="IntVersion" type="com.sunopsis.sql.DbInt"><![CDATA[1]]></Field>
	<Field name="ICol" type="com.sunopsis.sql.DbInt"><![CDATA[28479]]></Field>
	<Field name="ISrcCol" type="com.sunopsis.sql.DbInt"><![CDATA[null]]></Field>
	<Field name="ITable" type="com.sunopsis.sql.DbInt"><![CDATA[597]]></Field>
	<Field name="ITxtColDesc" type="com.sunopsis.sql.DbInt"><![CDATA[null]]></Field>
	<Field name="LastDate" type="java.sql.Timestamp"><![CDATA[2017-02-17 15:27:01.0]]></Field>
	<Field name="LastUser" type="java.lang.String"><![CDATA[SUPERVISOR]]></Field>
	<Field name="Longc" type="com.sunopsis.sql.DbInt"><![CDATA[50]]></Field>
	<Field name="Pos" type="com.sunopsis.sql.DbInt"><![CDATA[18]]></Field>
	<Field name="RecCodeList" type="java.lang.String">null</Field>
	<Field name="Scalec" type="com.sunopsis.sql.DbInt"><![CDATA[null]]></Field>
	<Field name="ScdColType" type="java.lang.String">null</Field>
	<Field name="SourceDt" type="java.lang.String"><![CDATA[VARCHAR2]]></Field>
</Object>
<Object class="com.sunopsis.dwg.dbobj.SnpCol">
		<Field name="Bytes" type="com.sunopsis.sql.DbInt"><![CDATA[0]]></Field>
	<Field name="CheckFlow" type="java.lang.String"><![CDATA[1]]></Field>
	<Field name="CheckStat" type="java.lang.String"><![CDATA[0]]></Field>
	<Field name="ColDecSep" type="java.lang.String">null</Field>
	<Field name="ColFormat" type="java.lang.String">null</Field>
	<Field name="ColHeading" type="java.lang.String"><![CDATA[CAUSING_CHANGE]]></Field>
	<Field name="ColMandatory" type="java.lang.String"><![CDATA[0]]></Field>
	<Field name="ColName" type="java.lang.String"><![CDATA[CAUSING_CHANGE]]></Field>
	<Field name="ColNullIfErr" type="java.lang.String">null</Field>
	<Field name="DataFormat" type="java.lang.String">null</Field>
	<Field name="DefValue" type="java.lang.String">null</Field>
	<Field name="ExtVersion" type="java.lang.String">null</Field>
	<Field name="FilePos" type="com.sunopsis.sql.DbInt"><![CDATA[null]]></Field>
	<Field name="FirstDate" type="java.sql.Timestamp"><![CDATA[2017-02-17 15:27:01.0]]></Field>
	<Field name="FirstUser" type="java.lang.String"><![CDATA[SUPERVISOR]]></Field>
	<Field name="GlobalId" type="java.lang.String"><![CDATA[3317f744-e4d8-42e3-8dea-4c6c67e0caa0]]></Field>
	<Field name="HbaseEncoding" type="java.lang.String">null</Field>
	<Field name="HiveSortbyPos" type="com.sunopsis.sql.DbInt"><![CDATA[null]]></Field>
	<Field name="IndChange" type="java.lang.String"><![CDATA[I]]></Field>
	<Field name="IndHiveCluster" type="java.lang.String">null</Field>
	<Field name="IndHivePartition" type="java.lang.String">null</Field>
	<Field name="IndHiveSort" type="java.lang.String">null</Field>
	<Field name="IndIn" type="java.lang.String">null</Field>
	<Field name="IndOut" type="java.lang.String">null</Field>
	<Field name="IndWrite" type="java.lang.String"><![CDATA[1]]></Field>
	<Field name="IndWsInsert" type="java.lang.String"><![CDATA[1]]></Field>
	<Field name="IndWsSelect" type="java.lang.String"><![CDATA[1]]></Field>
	<Field name="IndWsUpdate" type="java.lang.String"><![CDATA[1]]></Field>
	<Field name="IntVersion" type="com.sunopsis.sql.DbInt"><![CDATA[1]]></Field>
	<Field name="ICol" type="com.sunopsis.sql.DbInt"><![CDATA[28478]]></Field>
	<Field name="ISrcCol" type="com.sunopsis.sql.DbInt"><![CDATA[null]]></Field>
	<Field name="ITable" type="com.sunopsis.sql.DbInt"><![CDATA[597]]></Field>
	<Field name="ITxtColDesc" type="com.sunopsis.sql.DbInt"><![CDATA[null]]></Field>
	<Field name="LastDate" type="java.sql.Timestamp"><![CDATA[2017-02-17 15:27:01.0]]></Field>
	<Field name="LastUser" type="java.lang.String"><![CDATA[SUPERVISOR]]></Field>
	<Field name="Longc" type="com.sunopsis.sql.DbInt"><![CDATA[2000]]></Field>
	<Field name="Pos" type="com.sunopsis.sql.DbInt"><![CDATA[19]]></Field>
	<Field name="RecCodeList" type="java.lang.String">null</Field>
	<Field name="Scalec" type="com.sunopsis.sql.DbInt"><![CDATA[null]]></Field>
	<Field name="ScdColType" type="java.lang.String">null</Field>
	<Field name="SourceDt" type="java.lang.String"><![CDATA[VARCHAR2]]></Field>
</Object>
<Object class="com.sunopsis.dwg.dbobj.SnpCol">
		<Field name="Bytes" type="com.sunopsis.sql.DbInt"><![CDATA[0]]></Field>
	<Field name="CheckFlow" type="java.lang.String"><![CDATA[1]]></Field>
	<Field name="CheckStat" type="java.lang.String"><![CDATA[0]]></Field>
	<Field name="ColDecSep" type="java.lang.String">null</Field>
	<Field name="ColFormat" type="java.lang.String">null</Field>
	<Field name="ColHeading" type="java.lang.String"><![CDATA[REOPEN_COUNT]]></Field>
	<Field name="ColMandatory" type="java.lang.String"><![CDATA[0]]></Field>
	<Field name="ColName" type="java.lang.String"><![CDATA[REOPEN_COUNT]]></Field>
	<Field name="ColNullIfErr" type="java.lang.String">null</Field>
	<Field name="DataFormat" type="java.lang.String">null</Field>
	<Field name="DefValue" type="java.lang.String">null</Field>
	<Field name="ExtVersion" type="java.lang.String">null</Field>
	<Field name="FilePos" type="com.sunopsis.sql.DbInt"><![CDATA[null]]></Field>
	<Field name="FirstDate" type="java.sql.Timestamp"><![CDATA[2017-02-17 15:27:01.0]]></Field>
	<Field name="FirstUser" type="java.lang.String"><![CDATA[SUPERVISOR]]></Field>
	<Field name="GlobalId" type="java.lang.String"><![CDATA[ee158528-0b06-4056-b36a-83c4aed338ad]]></Field>
	<Field name="HbaseEncoding" type="java.lang.String">null</Field>
	<Field name="HiveSortbyPos" type="com.sunopsis.sql.DbInt"><![CDATA[null]]></Field>
	<Field name="IndChange" type="java.lang.String"><![CDATA[I]]></Field>
	<Field name="IndHiveCluster" type="java.lang.String">null</Field>
	<Field name="IndHivePartition" type="java.lang.String">null</Field>
	<Field name="IndHiveSort" type="java.lang.String">null</Field>
	<Field name="IndIn" type="java.lang.String">null</Field>
	<Field name="IndOut" type="java.lang.String">null</Field>
	<Field name="IndWrite" type="java.lang.String"><![CDATA[1]]></Field>
	<Field name="IndWsInsert" type="java.lang.String"><![CDATA[1]]></Field>
	<Field name="IndWsSelect" type="java.lang.String"><![CDATA[1]]></Field>
	<Field name="IndWsUpdate" type="java.lang.String"><![CDATA[1]]></Field>
	<Field name="IntVersion" type="com.sunopsis.sql.DbInt"><![CDATA[1]]></Field>
	<Field name="ICol" type="com.sunopsis.sql.DbInt"><![CDATA[28490]]></Field>
	<Field name="ISrcCol" type="com.sunopsis.sql.DbInt"><![CDATA[null]]></Field>
	<Field name="ITable" type="com.sunopsis.sql.DbInt"><![CDATA[597]]></Field>
	<Field name="ITxtColDesc" type="com.sunopsis.sql.DbInt"><![CDATA[null]]></Field>
	<Field name="LastDate" type="java.sql.Timestamp"><![CDATA[2017-02-17 15:27:01.0]]></Field>
	<Field name="LastUser" type="java.lang.String"><![CDATA[SUPERVISOR]]></Field>
	<Field name="Longc" type="com.sunopsis.sql.DbInt"><![CDATA[50]]></Field>
	<Field name="Pos" type="com.sunopsis.sql.DbInt"><![CDATA[20]]></Field>
	<Field name="RecCodeList" type="java.lang.String">null</Field>
	<Field name="Scalec" type="com.sunopsis.sql.DbInt"><![CDATA[null]]></Field>
	<Field name="ScdColType" type="java.lang.String">null</Field>
	<Field name="SourceDt" type="java.lang.String"><![CDATA[VARCHAR2]]></Field>
</Object>
<Object class="com.sunopsis.dwg.dbobj.SnpCol">
		<Field name="Bytes" type="com.sunopsis.sql.DbInt"><![CDATA[0]]></Field>
	<Field name="CheckFlow" type="java.lang.String"><![CDATA[1]]></Field>
	<Field name="CheckStat" type="java.lang.String"><![CDATA[0]]></Field>
	<Field name="ColDecSep" type="java.lang.String">null</Field>
	<Field name="ColFormat" type="java.lang.String">null</Field>
	<Field name="ColHeading" type="java.lang.String"><![CDATA[RESOLVE_CODE]]></Field>
	<Field name="ColMandatory" type="java.lang.String"><![CDATA[0]]></Field>
	<Field name="ColName" type="java.lang.String"><![CDATA[RESOLVE_CODE]]></Field>
	<Field name="ColNullIfErr" type="java.lang.String">null</Field>
	<Field name="DataFormat" type="java.lang.String">null</Field>
	<Field name="DefValue" type="java.lang.String">null</Field>
	<Field name="ExtVersion" type="java.lang.String">null</Field>
	<Field name="FilePos" type="com.sunopsis.sql.DbInt"><![CDATA[null]]></Field>
	<Field name="FirstDate" type="java.sql.Timestamp"><![CDATA[2017-02-17 15:27:02.0]]></Field>
	<Field name="FirstUser" type="java.lang.String"><![CDATA[SUPERVISOR]]></Field>
	<Field name="GlobalId" type="java.lang.String"><![CDATA[c58cea47-d029-43ac-a5b1-d706571807b1]]></Field>
	<Field name="HbaseEncoding" type="java.lang.String">null</Field>
	<Field name="HiveSortbyPos" type="com.sunopsis.sql.DbInt"><![CDATA[null]]></Field>
	<Field name="IndChange" type="java.lang.String"><![CDATA[I]]></Field>
	<Field name="IndHiveCluster" type="java.lang.String">null</Field>
	<Field name="IndHivePartition" type="java.lang.String">null</Field>
	<Field name="IndHiveSort" type="java.lang.String">null</Field>
	<Field name="IndIn" type="java.lang.String">null</Field>
	<Field name="IndOut" type="java.lang.String">null</Field>
	<Field name="IndWrite" type="java.lang.String"><![CDATA[1]]></Field>
	<Field name="IndWsInsert" type="java.lang.String"><![CDATA[1]]></Field>
	<Field name="IndWsSelect" type="java.lang.String"><![CDATA[1]]></Field>
	<Field name="IndWsUpdate" type="java.lang.String"><![CDATA[1]]></Field>
	<Field name="IntVersion" type="com.sunopsis.sql.DbInt"><![CDATA[1]]></Field>
	<Field name="ICol" type="com.sunopsis.sql.DbInt"><![CDATA[28493]]></Field>
	<Field name="ISrcCol" type="com.sunopsis.sql.DbInt"><![CDATA[null]]></Field>
	<Field name="ITable" type="com.sunopsis.sql.DbInt"><![CDATA[597]]></Field>
	<Field name="ITxtColDesc" type="com.sunopsis.sql.DbInt"><![CDATA[null]]></Field>
	<Field name="LastDate" type="java.sql.Timestamp"><![CDATA[2017-02-17 15:27:02.0]]></Field>
	<Field name="LastUser" type="java.lang.String"><![CDATA[SUPERVISOR]]></Field>
	<Field name="Longc" type="com.sunopsis.sql.DbInt"><![CDATA[50]]></Field>
	<Field name="Pos" type="com.sunopsis.sql.DbInt"><![CDATA[21]]></Field>
	<Field name="RecCodeList" type="java.lang.String">null</Field>
	<Field name="Scalec" type="com.sunopsis.sql.DbInt"><![CDATA[null]]></Field>
	<Field name="ScdColType" type="java.lang.String">null</Field>
	<Field name="SourceDt" type="java.lang.String"><![CDATA[VARCHAR2]]></Field>
</Object>
<Object class="com.sunopsis.dwg.dbobj.SnpCol">
		<Field name="Bytes" type="com.sunopsis.sql.DbInt"><![CDATA[0]]></Field>
	<Field name="CheckFlow" type="java.lang.String"><![CDATA[1]]></Field>
	<Field name="CheckStat" type="java.lang.String"><![CDATA[0]]></Field>
	<Field name="ColDecSep" type="java.lang.String">null</Field>
	<Field name="ColFormat" type="java.lang.String">null</Field>
	<Field name="ColHeading" type="java.lang.String"><![CDATA[REOPENED]]></Field>
	<Field name="ColMandatory" type="java.lang.String"><![CDATA[0]]></Field>
	<Field name="ColName" type="java.lang.String"><![CDATA[REOPENED]]></Field>
	<Field name="ColNullIfErr" type="java.lang.String">null</Field>
	<Field name="DataFormat" type="java.lang.String">null</Field>
	<Field name="DefValue" type="java.lang.String">null</Field>
	<Field name="ExtVersion" type="java.lang.String">null</Field>
	<Field name="FilePos" type="com.sunopsis.sql.DbInt"><![CDATA[null]]></Field>
	<Field name="FirstDate" type="java.sql.Timestamp"><![CDATA[2017-02-17 15:27:01.0]]></Field>
	<Field name="FirstUser" type="java.lang.String"><![CDATA[SUPERVISOR]]></Field>
	<Field name="GlobalId" type="java.lang.String"><![CDATA[8f0b3852-9a0c-447f-8075-10ed3b62ed2f]]></Field>
	<Field name="HbaseEncoding" type="java.lang.String">null</Field>
	<Field name="HiveSortbyPos" type="com.sunopsis.sql.DbInt"><![CDATA[null]]></Field>
	<Field name="IndChange" type="java.lang.String"><![CDATA[I]]></Field>
	<Field name="IndHiveCluster" type="java.lang.String">null</Field>
	<Field name="IndHivePartition" type="java.lang.String">null</Field>
	<Field name="IndHiveSort" type="java.lang.String">null</Field>
	<Field name="IndIn" type="java.lang.String">null</Field>
	<Field name="IndOut" type="java.lang.String">null</Field>
	<Field name="IndWrite" type="java.lang.String"><![CDATA[1]]></Field>
	<Field name="IndWsInsert" type="java.lang.String"><![CDATA[1]]></Field>
	<Field name="IndWsSelect" type="java.lang.String"><![CDATA[1]]></Field>
	<Field name="IndWsUpdate" type="java.lang.String"><![CDATA[1]]></Field>
	<Field name="IntVersion" type="com.sunopsis.sql.DbInt"><![CDATA[1]]></Field>
	<Field name="ICol" type="com.sunopsis.sql.DbInt"><![CDATA[28489]]></Field>
	<Field name="ISrcCol" type="com.sunopsis.sql.DbInt"><![CDATA[null]]></Field>
	<Field name="ITable" type="com.sunopsis.sql.DbInt"><![CDATA[597]]></Field>
	<Field name="ITxtColDesc" type="com.sunopsis.sql.DbInt"><![CDATA[null]]></Field>
	<Field name="LastDate" type="java.sql.Timestamp"><![CDATA[2017-02-17 15:27:01.0]]></Field>
	<Field name="LastUser" type="java.lang.String"><![CDATA[SUPERVISOR]]></Field>
	<Field name="Longc" type="com.sunopsis.sql.DbInt"><![CDATA[50]]></Field>
	<Field name="Pos" type="com.sunopsis.sql.DbInt"><![CDATA[22]]></Field>
	<Field name="RecCodeList" type="java.lang.String">null</Field>
	<Field name="Scalec" type="com.sunopsis.sql.DbInt"><![CDATA[null]]></Field>
	<Field name="ScdColType" type="java.lang.String">null</Field>
	<Field name="SourceDt" type="java.lang.String"><![CDATA[VARCHAR2]]></Field>
</Object>
<Object class="com.sunopsis.dwg.dbobj.SnpCol">
		<Field name="Bytes" type="com.sunopsis.sql.DbInt"><![CDATA[0]]></Field>
	<Field name="CheckFlow" type="java.lang.String"><![CDATA[1]]></Field>
	<Field name="CheckStat" type="java.lang.String"><![CDATA[0]]></Field>
	<Field name="ColDecSep" type="java.lang.String">null</Field>
	<Field name="ColFormat" type="java.lang.String">null</Field>
	<Field name="ColHeading" type="java.lang.String"><![CDATA[SYMPTOM]]></Field>
	<Field name="ColMandatory" type="java.lang.String"><![CDATA[0]]></Field>
	<Field name="ColName" type="java.lang.String"><![CDATA[SYMPTOM]]></Field>
	<Field name="ColNullIfErr" type="java.lang.String">null</Field>
	<Field name="DataFormat" type="java.lang.String">null</Field>
	<Field name="DefValue" type="java.lang.String">null</Field>
	<Field name="ExtVersion" type="java.lang.String">null</Field>
	<Field name="FilePos" type="com.sunopsis.sql.DbInt"><![CDATA[null]]></Field>
	<Field name="FirstDate" type="java.sql.Timestamp"><![CDATA[2017-02-17 15:27:02.0]]></Field>
	<Field name="FirstUser" type="java.lang.String"><![CDATA[SUPERVISOR]]></Field>
	<Field name="GlobalId" type="java.lang.String"><![CDATA[56b50514-2bd0-48f8-84fe-46b88682805a]]></Field>
	<Field name="HbaseEncoding" type="java.lang.String">null</Field>
	<Field name="HiveSortbyPos" type="com.sunopsis.sql.DbInt"><![CDATA[null]]></Field>
	<Field name="IndChange" type="java.lang.String"><![CDATA[I]]></Field>
	<Field name="IndHiveCluster" type="java.lang.String">null</Field>
	<Field name="IndHivePartition" type="java.lang.String">null</Field>
	<Field name="IndHiveSort" type="java.lang.String">null</Field>
	<Field name="IndIn" type="java.lang.String">null</Field>
	<Field name="IndOut" type="java.lang.String">null</Field>
	<Field name="IndWrite" type="java.lang.String"><![CDATA[1]]></Field>
	<Field name="IndWsInsert" type="java.lang.String"><![CDATA[1]]></Field>
	<Field name="IndWsSelect" type="java.lang.String"><![CDATA[1]]></Field>
	<Field name="IndWsUpdate" type="java.lang.String"><![CDATA[1]]></Field>
	<Field name="IntVersion" type="com.sunopsis.sql.DbInt"><![CDATA[1]]></Field>
	<Field name="ICol" type="com.sunopsis.sql.DbInt"><![CDATA[28500]]></Field>
	<Field name="ISrcCol" type="com.sunopsis.sql.DbInt"><![CDATA[null]]></Field>
	<Field name="ITable" type="com.sunopsis.sql.DbInt"><![CDATA[597]]></Field>
	<Field name="ITxtColDesc" type="com.sunopsis.sql.DbInt"><![CDATA[null]]></Field>
	<Field name="LastDate" type="java.sql.Timestamp"><![CDATA[2017-02-17 15:27:02.0]]></Field>
	<Field name="LastUser" type="java.lang.String"><![CDATA[SUPERVISOR]]></Field>
	<Field name="Longc" type="com.sunopsis.sql.DbInt"><![CDATA[200]]></Field>
	<Field name="Pos" type="com.sunopsis.sql.DbInt"><![CDATA[23]]></Field>
	<Field name="RecCodeList" type="java.lang.String">null</Field>
	<Field name="Scalec" type="com.sunopsis.sql.DbInt"><![CDATA[null]]></Field>
	<Field name="ScdColType" type="java.lang.String">null</Field>
	<Field name="SourceDt" type="java.lang.String"><![CDATA[VARCHAR2]]></Field>
</Object>
<Object class="com.sunopsis.dwg.dbobj.SnpCol">
		<Field name="Bytes" type="com.sunopsis.sql.DbInt"><![CDATA[0]]></Field>
	<Field name="CheckFlow" type="java.lang.String"><![CDATA[1]]></Field>
	<Field name="CheckStat" type="java.lang.String"><![CDATA[0]]></Field>
	<Field name="ColDecSep" type="java.lang.String">null</Field>
	<Field name="ColFormat" type="java.lang.String">null</Field>
	<Field name="ColHeading" type="java.lang.String"><![CDATA[SET_TO_P1]]></Field>
	<Field name="ColMandatory" type="java.lang.String"><![CDATA[0]]></Field>
	<Field name="ColName" type="java.lang.String"><![CDATA[SET_TO_P1]]></Field>
	<Field name="ColNullIfErr" type="java.lang.String">null</Field>
	<Field name="DataFormat" type="java.lang.String">null</Field>
	<Field name="DefValue" type="java.lang.String">null</Field>
	<Field name="ExtVersion" type="java.lang.String">null</Field>
	<Field name="FilePos" type="com.sunopsis.sql.DbInt"><![CDATA[null]]></Field>
	<Field name="FirstDate" type="java.sql.Timestamp"><![CDATA[2017-02-17 15:27:02.0]]></Field>
	<Field name="FirstUser" type="java.lang.String"><![CDATA[SUPERVISOR]]></Field>
	<Field name="GlobalId" type="java.lang.String"><![CDATA[83495e51-b6e7-41d1-bafd-3628fed8bf3e]]></Field>
	<Field name="HbaseEncoding" type="java.lang.String">null</Field>
	<Field name="HiveSortbyPos" type="com.sunopsis.sql.DbInt"><![CDATA[null]]></Field>
	<Field name="IndChange" type="java.lang.String"><![CDATA[I]]></Field>
	<Field name="IndHiveCluster" type="java.lang.String">null</Field>
	<Field name="IndHivePartition" type="java.lang.String">null</Field>
	<Field name="IndHiveSort" type="java.lang.String">null</Field>
	<Field name="IndIn" type="java.lang.String">null</Field>
	<Field name="IndOut" type="java.lang.String">null</Field>
	<Field name="IndWrite" type="java.lang.String"><![CDATA[1]]></Field>
	<Field name="IndWsInsert" type="java.lang.String"><![CDATA[1]]></Field>
	<Field name="IndWsSelect" type="java.lang.String"><![CDATA[1]]></Field>
	<Field name="IndWsUpdate" type="java.lang.String"><![CDATA[1]]></Field>
	<Field name="IntVersion" type="com.sunopsis.sql.DbInt"><![CDATA[1]]></Field>
	<Field name="ICol" type="com.sunopsis.sql.DbInt"><![CDATA[28495]]></Field>
	<Field name="ISrcCol" type="com.sunopsis.sql.DbInt"><![CDATA[null]]></Field>
	<Field name="ITable" type="com.sunopsis.sql.DbInt"><![CDATA[597]]></Field>
	<Field name="ITxtColDesc" type="com.sunopsis.sql.DbInt"><![CDATA[null]]></Field>
	<Field name="LastDate" type="java.sql.Timestamp"><![CDATA[2017-02-17 15:27:02.0]]></Field>
	<Field name="LastUser" type="java.lang.String"><![CDATA[SUPERVISOR]]></Field>
	<Field name="Longc" type="com.sunopsis.sql.DbInt"><![CDATA[50]]></Field>
	<Field name="Pos" type="com.sunopsis.sql.DbInt"><![CDATA[24]]></Field>
	<Field name="RecCodeList" type="java.lang.String">null</Field>
	<Field name="Scalec" type="com.sunopsis.sql.DbInt"><![CDATA[null]]></Field>
	<Field name="ScdColType" type="java.lang.String">null</Field>
	<Field name="SourceDt" type="java.lang.String"><![CDATA[VARCHAR2]]></Field>
</Object>
<Object class="com.sunopsis.dwg.dbobj.SnpCol">
		<Field name="Bytes" type="com.sunopsis.sql.DbInt"><![CDATA[0]]></Field>
	<Field name="CheckFlow" type="java.lang.String"><![CDATA[1]]></Field>
	<Field name="CheckStat" type="java.lang.String"><![CDATA[0]]></Field>
	<Field name="ColDecSep" type="java.lang.String">null</Field>
	<Field name="ColFormat" type="java.lang.String">null</Field>
	<Field name="ColHeading" type="java.lang.String"><![CDATA[SLA_DUE]]></Field>
	<Field name="ColMandatory" type="java.lang.String"><![CDATA[0]]></Field>
	<Field name="ColName" type="java.lang.String"><![CDATA[SLA_DUE]]></Field>
	<Field name="ColNullIfErr" type="java.lang.String">null</Field>
	<Field name="DataFormat" type="java.lang.String">null</Field>
	<Field name="DefValue" type="java.lang.String">null</Field>
	<Field name="ExtVersion" type="java.lang.String">null</Field>
	<Field name="FilePos" type="com.sunopsis.sql.DbInt"><![CDATA[null]]></Field>
	<Field name="FirstDate" type="java.sql.Timestamp"><![CDATA[2017-02-17 15:27:02.0]]></Field>
	<Field name="FirstUser" type="java.lang.String"><![CDATA[SUPERVISOR]]></Field>
	<Field name="GlobalId" type="java.lang.String"><![CDATA[7ccca96c-6aa3-450f-af46-8b03c4fc4a54]]></Field>
	<Field name="HbaseEncoding" type="java.lang.String">null</Field>
	<Field name="HiveSortbyPos" type="com.sunopsis.sql.DbInt"><![CDATA[null]]></Field>
	<Field name="IndChange" type="java.lang.String"><![CDATA[I]]></Field>
	<Field name="IndHiveCluster" type="java.lang.String">null</Field>
	<Field name="IndHivePartition" type="java.lang.String">null</Field>
	<Field name="IndHiveSort" type="java.lang.String">null</Field>
	<Field name="IndIn" type="java.lang.String">null</Field>
	<Field name="IndOut" type="java.lang.String">null</Field>
	<Field name="IndWrite" type="java.lang.String"><![CDATA[1]]></Field>
	<Field name="IndWsInsert" type="java.lang.String"><![CDATA[1]]></Field>
	<Field name="IndWsSelect" type="java.lang.String"><![CDATA[1]]></Field>
	<Field name="IndWsUpdate" type="java.lang.String"><![CDATA[1]]></Field>
	<Field name="IntVersion" type="com.sunopsis.sql.DbInt"><![CDATA[1]]></Field>
	<Field name="ICol" type="com.sunopsis.sql.DbInt"><![CDATA[28497]]></Field>
	<Field name="ISrcCol" type="com.sunopsis.sql.DbInt"><![CDATA[null]]></Field>
	<Field name="ITable" type="com.sunopsis.sql.DbInt"><![CDATA[597]]></Field>
	<Field name="ITxtColDesc" type="com.sunopsis.sql.DbInt"><![CDATA[null]]></Field>
	<Field name="LastDate" type="java.sql.Timestamp"><![CDATA[2017-02-17 15:27:02.0]]></Field>
	<Field name="LastUser" type="java.lang.String"><![CDATA[SUPERVISOR]]></Field>
	<Field name="Longc" type="com.sunopsis.sql.DbInt"><![CDATA[null]]></Field>
	<Field name="Pos" type="com.sunopsis.sql.DbInt"><![CDATA[25]]></Field>
	<Field name="RecCodeList" type="java.lang.String">null</Field>
	<Field name="Scalec" type="com.sunopsis.sql.DbInt"><![CDATA[null]]></Field>
	<Field name="ScdColType" type="java.lang.String">null</Field>
	<Field name="SourceDt" type="java.lang.String"><![CDATA[DATE]]></Field>
</Object>
<Object class="com.sunopsis.dwg.dbobj.SnpCol">
		<Field name="Bytes" type="com.sunopsis.sql.DbInt"><![CDATA[0]]></Field>
	<Field name="CheckFlow" type="java.lang.String"><![CDATA[1]]></Field>
	<Field name="CheckStat" type="java.lang.String"><![CDATA[0]]></Field>
	<Field name="ColDecSep" type="java.lang.String">null</Field>
	<Field name="ColFormat" type="java.lang.String">null</Field>
	<Field name="ColHeading" type="java.lang.String"><![CDATA[SLA_MET]]></Field>
	<Field name="ColMandatory" type="java.lang.String"><![CDATA[0]]></Field>
	<Field name="ColName" type="java.lang.String"><![CDATA[SLA_MET]]></Field>
	<Field name="ColNullIfErr" type="java.lang.String">null</Field>
	<Field name="DataFormat" type="java.lang.String">null</Field>
	<Field name="DefValue" type="java.lang.String">null</Field>
	<Field name="ExtVersion" type="java.lang.String">null</Field>
	<Field name="FilePos" type="com.sunopsis.sql.DbInt"><![CDATA[null]]></Field>
	<Field name="FirstDate" type="java.sql.Timestamp"><![CDATA[2017-02-17 15:27:02.0]]></Field>
	<Field name="FirstUser" type="java.lang.String"><![CDATA[SUPERVISOR]]></Field>
	<Field name="GlobalId" type="java.lang.String"><![CDATA[53fdd830-2931-4565-a239-c89424b50a4a]]></Field>
	<Field name="HbaseEncoding" type="java.lang.String">null</Field>
	<Field name="HiveSortbyPos" type="com.sunopsis.sql.DbInt"><![CDATA[null]]></Field>
	<Field name="IndChange" type="java.lang.String"><![CDATA[I]]></Field>
	<Field name="IndHiveCluster" type="java.lang.String">null</Field>
	<Field name="IndHivePartition" type="java.lang.String">null</Field>
	<Field name="IndHiveSort" type="java.lang.String">null</Field>
	<Field name="IndIn" type="java.lang.String">null</Field>
	<Field name="IndOut" type="java.lang.String">null</Field>
	<Field name="IndWrite" type="java.lang.String"><![CDATA[1]]></Field>
	<Field name="IndWsInsert" type="java.lang.String"><![CDATA[1]]></Field>
	<Field name="IndWsSelect" type="java.lang.String"><![CDATA[1]]></Field>
	<Field name="IndWsUpdate" type="java.lang.String"><![CDATA[1]]></Field>
	<Field name="IntVersion" type="com.sunopsis.sql.DbInt"><![CDATA[1]]></Field>
	<Field name="ICol" type="com.sunopsis.sql.DbInt"><![CDATA[28498]]></Field>
	<Field name="ISrcCol" type="com.sunopsis.sql.DbInt"><![CDATA[null]]></Field>
	<Field name="ITable" type="com.sunopsis.sql.DbInt"><![CDATA[597]]></Field>
	<Field name="ITxtColDesc" type="com.sunopsis.sql.DbInt"><![CDATA[null]]></Field>
	<Field name="LastDate" type="java.sql.Timestamp"><![CDATA[2017-02-17 15:27:02.0]]></Field>
	<Field name="LastUser" type="java.lang.String"><![CDATA[SUPERVISOR]]></Field>
	<Field name="Longc" type="com.sunopsis.sql.DbInt"><![CDATA[50]]></Field>
	<Field name="Pos" type="com.sunopsis.sql.DbInt"><![CDATA[26]]></Field>
	<Field name="RecCodeList" type="java.lang.String">null</Field>
	<Field name="Scalec" type="com.sunopsis.sql.DbInt"><![CDATA[null]]></Field>
	<Field name="ScdColType" type="java.lang.String">null</Field>
	<Field name="SourceDt" type="java.lang.String"><![CDATA[VARCHAR2]]></Field>
</Object>
<Object class="com.sunopsis.dwg.dbobj.SnpKey">
		<Field name="CheckFlow" type="java.lang.String"><![CDATA[1]]></Field>
	<Field name="CheckStat" type="java.lang.String"><![CDATA[1]]></Field>
	<Field name="ConsType" type="java.lang.String"><![CDATA[PK]]></Field>
	<Field name="ExtVersion" type="java.lang.String">null</Field>
	<Field name="FirstDate" type="java.sql.Timestamp"><![CDATA[2017-02-17 15:27:02.0]]></Field>
	<Field name="FirstUser" type="java.lang.String"><![CDATA[SUPERVISOR]]></Field>
	<Field name="GlobalId" type="java.lang.String"><![CDATA[dc4a50f4-f41a-4b1d-88c6-c62ed2d916d7]]></Field>
	<Field name="IndActive" type="java.lang.String"><![CDATA[1]]></Field>
	<Field name="IndChange" type="java.lang.String"><![CDATA[U]]></Field>
	<Field name="IndDb" type="java.lang.String"><![CDATA[1]]></Field>
	<Field name="IntVersion" type="com.sunopsis.sql.DbInt"><![CDATA[1]]></Field>
	<Field name="IKey" type="com.sunopsis.sql.DbInt"><![CDATA[2303]]></Field>
	<Field name="ITable" type="com.sunopsis.sql.DbInt"><![CDATA[597]]></Field>
	<Field name="KeyName" type="java.lang.String"><![CDATA[INCIDENT_NUMBER]]></Field>
	<Field name="LastDate" type="java.sql.Timestamp"><![CDATA[2017-02-17 15:27:02.0]]></Field>
	<Field name="LastUser" type="java.lang.String"><![CDATA[SUPERVISOR]]></Field>
</Object>
<Object class="com.sunopsis.dwg.dbobj.SnpKeyCol">
		<Field name="FirstDate" type="java.sql.Timestamp"><![CDATA[2017-02-17 15:27:02.0]]></Field>
	<Field name="FirstUser" type="java.lang.String"><![CDATA[SUPERVISOR]]></Field>
	<Field name="GlobalId" type="java.lang.String"><![CDATA[63e90079-3ae1-4ee6-bb75-6e2841de4045]]></Field>
	<Field name="IndChange" type="java.lang.String"><![CDATA[I]]></Field>
	<Field name="IntVersion" type="com.sunopsis.sql.DbInt"><![CDATA[1]]></Field>
	<Field name="ICol" type="com.sunopsis.sql.DbInt"><![CDATA[28484]]></Field>
	<Field name="IKey" type="com.sunopsis.sql.DbInt"><![CDATA[2303]]></Field>
	<Field name="LastDate" type="java.sql.Timestamp"><![CDATA[2017-02-17 15:27:02.0]]></Field>
	<Field name="LastUser" type="java.lang.String"><![CDATA[SUPERVISOR]]></Field>
	<Field name="Pos" type="com.sunopsis.sql.DbInt"><![CDATA[1]]></Field>
</Object>
<Object class="com.sunopsis.dwg.dbobj.SnpReferencedObject">
		<Field name="IObject" type="com.sunopsis.sql.DbInt"><![CDATA[2600]]></Field>
	<Field name="ObjectPKasString" type="java.lang.String"><![CDATA[28484]]></Field>
	<Field name="ObjectAKasString" type="java.lang.String"><![CDATA[597#INCIDENT_NUMBER]]></Field>
	<Field name="Description" type="java.lang.String"><![CDATA[SNP_MODFOLDER : DS_OBAW_DW #SNP_MODFOLDER : DS_OBAW_DW #SNP_MODEL : DS_OBAW_DW #SNP_SUBMODEL : Global #SNP_TABLE : OPR_INCIDENT_DTLS #SNP_COL : INCIDENT_NUMBER]]></Field>
 <Field name="GlobalId" type="java.lang.String"><![CDATA[3c3a52c6-8abb-4c9b-86ce-400007a671a3]]></Field>
</Object>
<Object class="com.sunopsis.dwg.dbobj.SnpFKXRef">
		<Field name="RefKey" type="java.lang.String"><![CDATA[SNP_SUBMODEL.95.166]]></Field>
	<Field name="RefObjGlobalId" type="java.lang.String"><![CDATA[4d7c72cd-c58b-44e3-ad2a-9592bcea4241]]></Field>
 <Field name="RefObjFQName" type="java.lang.String"><![CDATA[DS_OBAW_DW.DS_OBAW_DW.DS_OBAW_DW.Global]]></Field>
 <Field name="RefObjFQType" type="java.lang.String"><![CDATA[SNP_MODFOLDER.SNP_MODFOLDER.SNP_MODEL.SNP_SUBMODEL]]></Field>
 <Field name="RefObjFQNameLengths" type="java.lang.String"><![CDATA[10.10.10.6]]></Field>
</Object>
<Object class="com.sunopsis.dwg.dbobj.SnpFKXRef">
		<Field name="RefKey" type="java.lang.String"><![CDATA[SNP_TABLE.597]]></Field>
	<Field name="RefObjGlobalId" type="java.lang.String"><![CDATA[35a37bac-712d-4394-8a0e-a8c20de2b96d]]></Field>
 <Field name="RefObjFQName" type="java.lang.String"><![CDATA[DS_OBAW_DW.DS_OBAW_DW.DS_OBAW_DW.Global.OPR_INCIDENT_DTLS]]></Field>
 <Field name="RefObjFQType" type="java.lang.String"><![CDATA[SNP_MODFOLDER.SNP_MODFOLDER.SNP_MODEL.SNP_SUBMODEL.SNP_TABLE]]></Field>
 <Field name="RefObjFQNameLengths" type="java.lang.String"><![CDATA[10.10.10.6.17]]></Field>
</Object>
<Object class="com.sunopsis.dwg.dbobj.SnpFKXRef">
		<Field name="RefKey" type="java.lang.String"><![CDATA[SNP_KEY.2303]]></Field>
	<Field name="RefObjGlobalId" type="java.lang.String"><![CDATA[dc4a50f4-f41a-4b1d-88c6-c62ed2d916d7]]></Field>
 <Field name="RefObjFQName" type="java.lang.String"><![CDATA[DS_OBAW_DW.DS_OBAW_DW.DS_OBAW_DW.Global.OPR_INCIDENT_DTLS.INCIDENT_NUMBER]]></Field>
 <Field name="RefObjFQType" type="java.lang.String"><![CDATA[SNP_MODFOLDER.SNP_MODFOLDER.SNP_MODEL.SNP_SUBMODEL.SNP_TABLE.SNP_KEY]]></Field>
 <Field name="RefObjFQNameLengths" type="java.lang.String"><![CDATA[10.10.10.6.17.15]]></Field>
</Object>
<Object class="com.sunopsis.dwg.dbobj.SnpFKXRef">
		<Field name="RefKey" type="java.lang.String"><![CDATA[SNP_COL.28484]]></Field>
	<Field name="RefObjGlobalId" type="java.lang.String"><![CDATA[3c3a52c6-8abb-4c9b-86ce-400007a671a3]]></Field>
 <Field name="RefObjFQName" type="java.lang.String"><![CDATA[DS_OBAW_DW.DS_OBAW_DW.DS_OBAW_DW.Global.OPR_INCIDENT_DTLS.INCIDENT_NUMBER]]></Field>
 <Field name="RefObjFQType" type="java.lang.String"><![CDATA[SNP_MODFOLDER.SNP_MODFOLDER.SNP_MODEL.SNP_SUBMODEL.SNP_TABLE.SNP_COL]]></Field>
 <Field name="RefObjFQNameLengths" type="java.lang.String"><![CDATA[10.10.10.6.17.15]]></Field>
</Object>
<Object class="com.sunopsis.dwg.DwgExportSummary">
		<Field name="ExpTxtNb" type="com.sunopsis.sql.DbInt"><![CDATA[0]]></Field>
	<Field name="InstObjNb" type="com.sunopsis.sql.DbInt"><![CDATA[0]]></Field>
	<Field name="JoinColNb" type="com.sunopsis.sql.DbInt"><![CDATA[0]]></Field>
	<Field name="JoinNb" type="com.sunopsis.sql.DbInt"><![CDATA[0]]></Field>
	<Field name="KeyColNb" type="com.sunopsis.sql.DbInt"><![CDATA[1]]></Field>
	<Field name="KeyNb" type="com.sunopsis.sql.DbInt"><![CDATA[1]]></Field>
	<Field name="LinkDiagNb" type="com.sunopsis.sql.DbInt"><![CDATA[0]]></Field>
	<Field name="MorigTxtNb" type="com.sunopsis.sql.DbInt"><![CDATA[0]]></Field>
	<Field name="MtxtNb" type="com.sunopsis.sql.DbInt"><![CDATA[0]]></Field>
	<Field name="OrigTxtNb" type="com.sunopsis.sql.DbInt"><![CDATA[0]]></Field>
	<Field name="OtherObjectsNb" type="com.sunopsis.sql.DbInt"><![CDATA[27]]></Field>
	<Field name="PlanAgentNb" type="com.sunopsis.sql.DbInt"><![CDATA[0]]></Field>
	<Field name="StepNb" type="com.sunopsis.sql.DbInt"><![CDATA[0]]></Field>
	<Field name="TxtNb" type="com.sunopsis.sql.DbInt"><![CDATA[0]]></Field>
	<Field name="UeOrigNb" type="com.sunopsis.sql.DbInt"><![CDATA[0]]></Field>
	<Field name="UeUsedNb" type="com.sunopsis.sql.DbInt"><![CDATA[0]]></Field>
	<Field name="VarPlanAgentNb" type="com.sunopsis.sql.DbInt"><![CDATA[0]]></Field>
	<Field name="ScenTxtNb" type="com.sunopsis.sql.DbInt"><![CDATA[0]]></Field>
	<Field name="OdiVersion" type="java.lang.String"><![CDATA[12.2.1]]></Field>
	<Field name="OriginRepositoryID" type="com.sunopsis.sql.DbInt"><![CDATA[1]]></Field>
	<Field name="RepositoryVersion" type="java.lang.String"><![CDATA[05.02.02.05]]></Field>
</Object>
</SunopsisExport>
